[{"model": "stock.stock", "pk": 1789, "fields": {"business": "\uac74\uc124\uc5c5", "title": "GS\uac74\uc124", "code": "006360", "yesterday_price": 27600, "price": 26800, "today_start_price": 27600, "max_price": 35850, "min_price": 19350, "high_price": 27600, "low_price": 26650, "change": -2.9, "deal": 615957, "today_graph": "http://chart.finance.daum.net/time3/real/006360-290157.png?date=201610260935", "month_graph": "http://chart.finance.daum.net/candle3/006360-290157.png?date=201610260935", "three_month_graph": "http://chart.finance.daum.net/time3/3month/006360-290157.png?date=201610260935", "year_graph": "http://chart.finance.daum.net/time3/year/006360-290157.png?date=201610260935"}}, {"model": "stock.stock", "pk": 1790, "fields": {"business": "\uac74\uc124\uc5c5", "title": "\uacc4\ub8e1\uac74\uc124", "code": "013580", "yesterday_price": 14600, "price": 14700, "today_start_price": 14700, "max_price": 18950, "min_price": 10250, "high_price": 14700, "low_price": 14500, "change": 0.68, "deal": 2249, "today_graph": "http://chart.finance.daum.net/time3/real/013580-290157.png?date=201610260935", "month_graph": "http://chart.finance.daum.net/candle3/013580-290157.png?date=201610260935", "three_month_graph": "http://chart.finance.daum.net/time3/3month/013580-290157.png?date=201610260935", "year_graph": "http://chart.finance.daum.net/time3/year/013580-290157.png?date=201610260935"}}, {"model": "stock.stock", "pk": 1791, "fields": {"business": "\uac74\uc124\uc5c5", "title": "\uace0\ub824\uac1c\ubc1c", "code": "004200", "yesterday_price": 7240, "price": 6860, "today_start_price": 7170, "max_price": 9410, "min_price": 5070, "high_price": 7170, "low_price": 6860, "change": -5.25, "deal": 6648, "today_graph": "http://chart.finance.daum.net/time3/real/004200-290157.png?date=201610260935", "month_graph": "http://chart.finance.daum.net/candle3/004200-290157.png?date=201610260935", "three_month_graph": "http://chart.finance.daum.net/time3/3month/004200-290157.png?date=201610260935", "year_graph": "http://chart.finance.daum.net/time3/year/004200-290157.png?date=201610260935"}}, {"model": "stock.stock", "pk": 1792, "fields": {"business": "\uac74\uc124\uc5c5", "title": "\uae08\ud638\uc0b0\uc5c5", "code": "002990", "yesterday_price": 10200, "price": 10250, "today_start_price": 10050, "max_price": 13250, "min_price": 7150, "high_price": 10250, "low_price": 10050, "change": 0.49, "deal": 5959, "today_graph": "http://chart.finance.daum.net/time3/real/002990-290157.png?date=201610260935", "month_graph": "http://chart.finance.daum.net/candle3/002990-290157.png?date=201610260935", "three_month_graph": "http://chart.finance.daum.net/time3/3month/002990-290157.png?date=201610260935", "year_graph": "http://chart.finance.daum.net/time3/year/002990-290157.png?date=201610260935"}}, {"model": "stock.stock", "pk": 1793, "fields": {"business": "\uac74\uc124\uc5c5", "title": "\uae08\ud638\uc0b0\uc5c5\uc6b0", "code": "002995", "yesterday_price": 20000, "price": 19550, "today_start_price": 20000, "max_price": 26000, "min_price": 14000, "high_price": 20000, "low_price": 19250, "change": -2.25, "deal": 362, "today_graph": "http://chart.finance.daum.net/time3/real/002995-290157.png?date=201610260935", "month_graph": "http://chart.finance.daum.net/candle3/002995-290157.png?date=201610260935", "three_month_graph": "http://chart.finance.daum.net/time3/3month/002995-290157.png?date=201610260935", "year_graph": "http://chart.finance.daum.net/time3/year/002995-290157.png?date=201610260935"}}, {"model": "stock.stock", "pk": 1794, "fields": {"business": "\uac74\uc124\uc5c5", "title": "\uae4c\ubba4\uc774\uc564\uc528", "code": "013700", "yesterday_price": 10800, "price": 10800, "today_start_price": 10800, "max_price": 14000, "min_price": 7600, "high_price": 10800, "low_price": 10800, "change": 0.0, "deal": 2, "today_graph": "http://chart.finance.daum.net/time3/real/013700-290157.png?date=201610260935", "month_graph": "http://chart.finance.daum.net/candle3/013700-290157.png?date=201610260935", "three_month_graph": "http://chart.finance.daum.net/time3/3month/013700-290157.png?date=201610260935", "year_graph": "http://chart.finance.daum.net/time3/year/013700-290157.png?date=201610260935"}}, {"model": "stock.stock", "pk": 1795, "fields": {"business": "\uac74\uc124\uc5c5", "title": "\ub0a8\uad11\ud1a0\uac74", "code": "001260", "yesterday_price": 8330, "price": 8350, "today_start_price": 8540, "max_price": 10800, "min_price": 5840, "high_price": 8540, "low_price": 8310, "change": 0.24, "deal": 4856, "today_graph": "http://chart.finance.daum.net/time3/real/001260-290157.png?date=201610260935", "month_graph": "http://chart.finance.daum.net/candle3/001260-290157.png?date=201610260935", "three_month_graph": "http://chart.finance.daum.net/time3/3month/001260-290157.png?date=201610260935", "year_graph": "http://chart.finance.daum.net/time3/year/001260-290157.png?date=201610260935"}}, {"model": "stock.stock", "pk": 1796, "fields": {"business": "\uac74\uc124\uc5c5", "title": "\ub300\ub9bc\uc0b0\uc5c5", "code": "000210", "yesterday_price": 89300, "price": 88500, "today_start_price": 89300, "max_price": 116000, "min_price": 62600, "high_price": 89900, "low_price": 88400, "change": -0.9, "deal": 17246, "today_graph": "http://chart.finance.daum.net/time3/real/000210-290157.png?date=201610260935", "month_graph": "http://chart.finance.daum.net/candle3/000210-290157.png?date=201610260935", "three_month_graph": "http://chart.finance.daum.net/time3/3month/000210-290157.png?date=201610260935", "year_graph": "http://chart.finance.daum.net/time3/year/000210-290157.png?date=201610260935"}}, {"model": "stock.stock", "pk": 1797, "fields": {"business": "\uac74\uc124\uc5c5", "title": "\ub300\ub9bc\uc0b0\uc5c5\uc6b0", "code": "000215", "yesterday_price": 30200, "price": 30250, "today_start_price": 30500, "max_price": 39250, "min_price": 21150, "high_price": 30500, "low_price": 30250, "change": 0.17, "deal": 476, "today_graph": "http://chart.finance.daum.net/time3/real/000215-290157.png?date=201610260935", "month_graph": "http://chart.finance.daum.net/candle3/000215-290157.png?date=201610260935", "three_month_graph": "http://chart.finance.daum.net/time3/3month/000215-290157.png?date=201610260935", "year_graph": "http://chart.finance.daum.net/time3/year/000215-290157.png?date=201610260935"}}, {"model": "stock.stock", "pk": 1798, "fields": {"business": "\uac74\uc124\uc5c5", "title": "\ub300\uc6b0\uac74\uc124", "code": "047040", "yesterday_price": 6550, "price": 6510, "today_start_price": 6560, "max_price": 8510, "min_price": 4590, "high_price": 6580, "low_price": 6510, "change": -0.61, "deal": 39768, "today_graph": "http://chart.finance.daum.net/time3/real/047040-290157.png?date=201610260935", "month_graph": "http://chart.finance.daum.net/candle3/047040-290157.png?date=201610260935", "three_month_graph": "http://chart.finance.daum.net/time3/3month/047040-290157.png?date=201610260935", "year_graph": "http://chart.finance.daum.net/time3/year/047040-290157.png?date=201610260935"}}, {"model": "stock.stock", "pk": 1799, "fields": {"business": "\uac74\uc124\uc5c5", "title": "\ub3d9\ubd80\uac74\uc124", "code": "005960", "yesterday_price": 10500, "price": 10500, "today_start_price": 0, "max_price": 13650, "min_price": 7350, "high_price": 0, "low_price": 0, "change": 0.0, "deal": 0, "today_graph": "http://chart.finance.daum.net/time3/real/005960-290157.png?date=201610260935", "month_graph": "http://chart.finance.daum.net/candle3/005960-290157.png?date=201610260935", "three_month_graph": "http://chart.finance.daum.net/time3/3month/005960-290157.png?date=201610260935", "year_graph": "http://chart.finance.daum.net/time3/year/005960-290157.png?date=201610260935"}}, {"model": "stock.stock", "pk": 1800, "fields": {"business": "\uac74\uc124\uc5c5", "title": "\ub3d9\ubd80\uac74\uc124\uc6b0", "code": "005965", "yesterday_price": 22200, "price": 22200, "today_start_price": 0, "max_price": 28850, "min_price": 15550, "high_price": 0, "low_price": 0, "change": 0.0, "deal": 0, "today_graph": "http://chart.finance.daum.net/time3/real/005965-290157.png?date=201610260935", "month_graph": "http://chart.finance.daum.net/candle3/005965-290157.png?date=201610260935", "three_month_graph": "http://chart.finance.daum.net/time3/3month/005965-290157.png?date=201610260935", "year_graph": "http://chart.finance.daum.net/time3/year/005965-290157.png?date=201610260935"}}, {"model": "stock.stock", "pk": 1801, "fields": {"business": "\uac74\uc124\uc5c5", "title": "\ub3d9\uc544\uc9c0\uc9c8", "code": "028100", "yesterday_price": 8690, "price": 8740, "today_start_price": 8690, "max_price": 11250, "min_price": 6090, "high_price": 8740, "low_price": 8670, "change": 0.58, "deal": 1912, "today_graph": "http://chart.finance.daum.net/time3/real/028100-290157.png?date=201610260935", "month_graph": "http://chart.finance.daum.net/candle3/028100-290157.png?date=201610260935", "three_month_graph": "http://chart.finance.daum.net/time3/3month/028100-290157.png?date=201610260935", "year_graph": "http://chart.finance.daum.net/time3/year/028100-290157.png?date=201610260935"}}, {"model": "stock.stock", "pk": 1802, "fields": {"business": "\uac74\uc124\uc5c5", "title": "\ub450\uc0b0\uac74\uc124", "code": "011160", "yesterday_price": 4160, "price": 4115, "today_start_price": 4160, "max_price": 5400, "min_price": 2915, "high_price": 4160, "low_price": 4110, "change": -1.08, "deal": 4763, "today_graph": "http://chart.finance.daum.net/time3/real/011160-290157.png?date=201610260935", "month_graph": "http://chart.finance.daum.net/candle3/011160-290157.png?date=201610260935", "three_month_graph": "http://chart.finance.daum.net/time3/3month/011160-290157.png?date=201610260935", "year_graph": "http://chart.finance.daum.net/time3/year/011160-290157.png?date=201610260935"}}, {"model": "stock.stock", "pk": 1803, "fields": {"business": "\uac74\uc124\uc5c5", "title": "\ubc94\uc591\uac74\uc601", "code": "002410", "yesterday_price": 13500, "price": 13500, "today_start_price": 13200, "max_price": 17550, "min_price": 9450, "high_price": 13650, "low_price": 13200, "change": 0.0, "deal": 3114, "today_graph": "http://chart.finance.daum.net/time3/real/002410-290157.png?date=201610260935", "month_graph": "http://chart.finance.daum.net/candle3/002410-290157.png?date=201610260935", "three_month_graph": "http://chart.finance.daum.net/time3/3month/002410-290157.png?date=201610260935", "year_graph": "http://chart.finance.daum.net/time3/year/002410-290157.png?date=201610260935"}}, {"model": "stock.stock", "pk": 1804, "fields": {"business": "\uac74\uc124\uc5c5", "title": "\uc0bc\ubd80\ud1a0\uac74", "code": "001470", "yesterday_price": 10750, "price": 11000, "today_start_price": 10800, "max_price": 13950, "min_price": 7550, "high_price": 11000, "low_price": 10600, "change": 2.33, "deal": 48634, "today_graph": "http://chart.finance.daum.net/time3/real/001470-290157.png?date=201610260935", "month_graph": "http://chart.finance.daum.net/candle3/001470-290157.png?date=201610260935", "three_month_graph": "http://chart.finance.daum.net/time3/3month/001470-290157.png?date=201610260935", "year_graph": "http://chart.finance.daum.net/time3/year/001470-290157.png?date=201610260935"}}, {"model": "stock.stock", "pk": 1805, "fields": {"business": "\uac74\uc124\uc5c5", "title": "\uc0bc\ud638", "code": "001880", "yesterday_price": 17450, "price": 17200, "today_start_price": 17150, "max_price": 22650, "min_price": 12250, "high_price": 17200, "low_price": 17000, "change": -1.43, "deal": 522, "today_graph": "http://chart.finance.daum.net/time3/real/001880-290157.png?date=201610260935", "month_graph": "http://chart.finance.daum.net/candle3/001880-290157.png?date=201610260935", "three_month_graph": "http://chart.finance.daum.net/time3/3month/001880-290157.png?date=201610260935", "year_graph": "http://chart.finance.daum.net/time3/year/001880-290157.png?date=201610260935"}}, {"model": "stock.stock", "pk": 1806, "fields": {"business": "\uac74\uc124\uc5c5", "title": "\uc0bc\ud638\uac1c\ubc1c", "code": "010960", "yesterday_price": 3470, "price": 3455, "today_start_price": 3470, "max_price": 4510, "min_price": 2430, "high_price": 3490, "low_price": 3455, "change": -0.43, "deal": 9414, "today_graph": "http://chart.finance.daum.net/time3/real/010960-290157.png?date=201610260935", "month_graph": "http://chart.finance.daum.net/candle3/010960-290157.png?date=201610260935", "three_month_graph": "http://chart.finance.daum.net/time3/3month/010960-290157.png?date=201610260935", "year_graph": "http://chart.finance.daum.net/time3/year/010960-290157.png?date=201610260935"}}, {"model": "stock.stock", "pk": 1807, "fields": {"business": "\uac74\uc124\uc5c5", "title": "\uc131\uc9c0\uac74\uc124", "code": "005980", "yesterday_price": 2030, "price": 2105, "today_start_price": 2140, "max_price": 2635, "min_price": 1425, "high_price": 2210, "low_price": 2065, "change": 3.69, "deal": 301633, "today_graph": "http://chart.finance.daum.net/time3/real/005980-290157.png?date=201610260935", "month_graph": "http://chart.finance.daum.net/candle3/005980-290157.png?date=201610260935", "three_month_graph": "http://chart.finance.daum.net/time3/3month/005980-290157.png?date=201610260935", "year_graph": "http://chart.finance.daum.net/time3/year/005980-290157.png?date=201610260935"}}, {"model": "stock.stock", "pk": 1808, "fields": {"business": "\uac74\uc124\uc5c5", "title": "\uc2e0\uc138\uacc4\uac74\uc124", "code": "034300", "yesterday_price": 40800, "price": 40650, "today_start_price": 40800, "max_price": 53000, "min_price": 28600, "high_price": 40950, "low_price": 40500, "change": -0.37, "deal": 164, "today_graph": "http://chart.finance.daum.net/time3/real/034300-290157.png?date=201610260935", "month_graph": "http://chart.finance.daum.net/candle3/034300-290157.png?date=201610260935", "three_month_graph": "http://chart.finance.daum.net/time3/3month/034300-290157.png?date=201610260935", "year_graph": "http://chart.finance.daum.net/time3/year/034300-290157.png?date=201610260935"}}, {"model": "stock.stock", "pk": 1809, "fields": {"business": "\uac74\uc124\uc5c5", "title": "\uc2e0\ud55c", "code": "005450", "yesterday_price": 5090, "price": 5050, "today_start_price": 5000, "max_price": 6610, "min_price": 3570, "high_price": 5060, "low_price": 4960, "change": -0.79, "deal": 1982, "today_graph": "http://chart.finance.daum.net/time3/real/005450-290157.png?date=201610260935", "month_graph": "http://chart.finance.daum.net/candle3/005450-290157.png?date=201610260935", "three_month_graph": "http://chart.finance.daum.net/time3/3month/005450-290157.png?date=201610260935", "year_graph": "http://chart.finance.daum.net/time3/year/005450-290157.png?date=201610260935"}}, {"model": "stock.stock", "pk": 1810, "fields": {"business": "\uac74\uc124\uc5c5", "title": "\uc544\uc774\ucf58\ud2b8\ub864\uc2a4", "code": "039570", "yesterday_price": 29250, "price": 29250, "today_start_price": 29450, "max_price": 38000, "min_price": 20500, "high_price": 29600, "low_price": 29250, "change": 0.0, "deal": 686, "today_graph": "http://chart.finance.daum.net/time3/real/039570-290157.png?date=201610260935", "month_graph": "http://chart.finance.daum.net/candle3/039570-290157.png?date=201610260935", "three_month_graph": "http://chart.finance.daum.net/time3/3month/039570-290157.png?date=201610260935", "year_graph": "http://chart.finance.daum.net/time3/year/039570-290157.png?date=201610260935"}}, {"model": "stock.stock", "pk": 1811, "fields": {"business": "\uac74\uc124\uc5c5", "title": "\uc5d0\uc4f0\uc528\uc5d4\uc9c0\ub2c8\uc5b4\ub9c1", "code": "023960", "yesterday_price": 3800, "price": 3770, "today_start_price": 3820, "max_price": 4940, "min_price": 2660, "high_price": 3880, "low_price": 3625, "change": -0.79, "deal": 7706, "today_graph": "http://chart.finance.daum.net/time3/real/023960-290157.png?date=201610260935", "month_graph": "http://chart.finance.daum.net/candle3/023960-290157.png?date=201610260935", "three_month_graph": "http://chart.finance.daum.net/time3/3month/023960-290157.png?date=201610260935", "year_graph": "http://chart.finance.daum.net/time3/year/023960-290157.png?date=201610260935"}}, {"model": "stock.stock", "pk": 1812, "fields": {"business": "\uac74\uc124\uc5c5", "title": "\uc77c\uc131\uac74\uc124", "code": "013360", "yesterday_price": 9600, "price": 9530, "today_start_price": 9550, "max_price": 12450, "min_price": 6720, "high_price": 9550, "low_price": 9530, "change": -0.73, "deal": 35, "today_graph": "http://chart.finance.daum.net/time3/real/013360-290157.png?date=201610260935", "month_graph": "http://chart.finance.daum.net/candle3/013360-290157.png?date=201610260935", "three_month_graph": "http://chart.finance.daum.net/time3/3month/013360-290157.png?date=201610260935", "year_graph": "http://chart.finance.daum.net/time3/year/013360-290157.png?date=201610260935"}}, {"model": "stock.stock", "pk": 1813, "fields": {"business": "\uac74\uc124\uc5c5", "title": "\uc77c\uc131\uac74\uc1242\uc6b0B", "code": "013367", "yesterday_price": 45400, "price": 43000, "today_start_price": 44200, "max_price": 59000, "min_price": 31800, "high_price": 44200, "low_price": 43000, "change": -5.29, "deal": 567, "today_graph": "http://chart.finance.daum.net/time3/real/013367-290157.png?date=201610260935", "month_graph": "http://chart.finance.daum.net/candle3/013367-290157.png?date=201610260935", "three_month_graph": "http://chart.finance.daum.net/time3/3month/013367-290157.png?date=201610260935", "year_graph": "http://chart.finance.daum.net/time3/year/013367-290157.png?date=201610260935"}}, {"model": "stock.stock", "pk": 1814, "fields": {"business": "\uac74\uc124\uc5c5", "title": "\uc9c4\ud765\uae30\uc5c5", "code": "002780", "yesterday_price": 1820, "price": 1810, "today_start_price": 1815, "max_price": 2365, "min_price": 1275, "high_price": 1815, "low_price": 1790, "change": -0.55, "deal": 2553, "today_graph": "http://chart.finance.daum.net/time3/real/002780-290157.png?date=201610260935", "month_graph": "http://chart.finance.daum.net/candle3/002780-290157.png?date=201610260935", "three_month_graph": "http://chart.finance.daum.net/time3/3month/002780-290157.png?date=201610260935", "year_graph": "http://chart.finance.daum.net/time3/year/002780-290157.png?date=201610260935"}}, {"model": "stock.stock", "pk": 1815, "fields": {"business": "\uac74\uc124\uc5c5", "title": "\uc9c4\ud765\uae30\uc5c52\uc6b0B", "code": "002787", "yesterday_price": 8900, "price": 8300, "today_start_price": 8500, "max_price": 11550, "min_price": 6230, "high_price": 8510, "low_price": 8170, "change": -6.74, "deal": 28450, "today_graph": "http://chart.finance.daum.net/time3/real/002787-290157.png?date=201610260935", "month_graph": "http://chart.finance.daum.net/candle3/002787-290157.png?date=201610260935", "three_month_graph": "http://chart.finance.daum.net/time3/3month/002787-290157.png?date=201610260935", "year_graph": "http://chart.finance.daum.net/time3/year/002787-290157.png?date=201610260935"}}, {"model": "stock.stock", "pk": 1816, "fields": {"business": "\uac74\uc124\uc5c5", "title": "\uc9c4\ud765\uae30\uc5c5\uc6b0B", "code": "002785", "yesterday_price": 3825, "price": 3700, "today_start_price": 3750, "max_price": 4970, "min_price": 2680, "high_price": 3840, "low_price": 3660, "change": -3.27, "deal": 9446, "today_graph": "http://chart.finance.daum.net/time3/real/002785-290157.png?date=201610260935", "month_graph": "http://chart.finance.daum.net/candle3/002785-290157.png?date=201610260935", "three_month_graph": "http://chart.finance.daum.net/time3/3month/002785-290157.png?date=201610260935", "year_graph": "http://chart.finance.daum.net/time3/year/002785-290157.png?date=201610260935"}}, {"model": "stock.stock", "pk": 1817, "fields": {"business": "\uac74\uc124\uc5c5", "title": "\ucf54\uc624\ub871\uae00\ub85c\ubc8c", "code": "003070", "yesterday_price": 13600, "price": 13300, "today_start_price": 13550, "max_price": 17650, "min_price": 9550, "high_price": 13550, "low_price": 13300, "change": -2.21, "deal": 453, "today_graph": "http://chart.finance.daum.net/time3/real/003070-290157.png?date=201610260935", "month_graph": "http://chart.finance.daum.net/candle3/003070-290157.png?date=201610260935", "three_month_graph": "http://chart.finance.daum.net/time3/3month/003070-290157.png?date=201610260935", "year_graph": "http://chart.finance.daum.net/time3/year/003070-290157.png?date=201610260935"}}, {"model": "stock.stock", "pk": 1818, "fields": {"business": "\uac74\uc124\uc5c5", "title": "\ucf54\uc624\ub871\uae00\ub85c\ubc8c\uc6b0", "code": "003075", "yesterday_price": 11550, "price": 11550, "today_start_price": 0, "max_price": 15000, "min_price": 8100, "high_price": 0, "low_price": 0, "change": 0.0, "deal": 0, "today_graph": "http://chart.finance.daum.net/time3/real/003075-290157.png?date=201610260935", "month_graph": "http://chart.finance.daum.net/candle3/003075-290157.png?date=201610260935", "three_month_graph": "http://chart.finance.daum.net/time3/3month/003075-290157.png?date=201610260935", "year_graph": "http://chart.finance.daum.net/time3/year/003075-290157.png?date=201610260935"}}, {"model": "stock.stock", "pk": 1819, "fields": {"business": "\uac74\uc124\uc5c5", "title": "\ud0dc\uc601\uac74\uc124", "code": "009410", "yesterday_price": 4875, "price": 4855, "today_start_price": 4855, "max_price": 6330, "min_price": 3415, "high_price": 4855, "low_price": 4850, "change": -0.41, "deal": 28376, "today_graph": "http://chart.finance.daum.net/time3/real/009410-290157.png?date=201610260935", "month_graph": "http://chart.finance.daum.net/candle3/009410-290157.png?date=201610260935", "three_month_graph": "http://chart.finance.daum.net/time3/3month/009410-290157.png?date=201610260935", "year_graph": "http://chart.finance.daum.net/time3/year/009410-290157.png?date=201610260935"}}, {"model": "stock.stock", "pk": 1820, "fields": {"business": "\uac74\uc124\uc5c5", "title": "\ud0dc\uc601\uac74\uc124\uc6b0", "code": "009415", "yesterday_price": 7600, "price": 6970, "today_start_price": 7070, "max_price": 9880, "min_price": 5320, "high_price": 7170, "low_price": 6600, "change": -8.29, "deal": 144964, "today_graph": "http://chart.finance.daum.net/time3/real/009415-290157.png?date=201610260935", "month_graph": "http://chart.finance.daum.net/candle3/009415-290157.png?date=201610260935", "three_month_graph": "http://chart.finance.daum.net/time3/3month/009415-290157.png?date=201610260935", "year_graph": "http://chart.finance.daum.net/time3/year/009415-290157.png?date=201610260935"}}, {"model": "stock.stock", "pk": 1821, "fields": {"business": "\uac74\uc124\uc5c5", "title": "\ud55c\ub77c", "code": "014790", "yesterday_price": 4640, "price": 4685, "today_start_price": 4640, "max_price": 6030, "min_price": 3250, "high_price": 4685, "low_price": 4550, "change": 0.97, "deal": 1229, "today_graph": "http://chart.finance.daum.net/time3/real/014790-290157.png?date=201610260935", "month_graph": "http://chart.finance.daum.net/candle3/014790-290157.png?date=201610260935", "three_month_graph": "http://chart.finance.daum.net/time3/3month/014790-290157.png?date=201610260935", "year_graph": "http://chart.finance.daum.net/time3/year/014790-290157.png?date=201610260935"}}, {"model": "stock.stock", "pk": 1822, "fields": {"business": "\uac74\uc124\uc5c5", "title": "\ud55c\uc2e0\uacf5\uc601", "code": "004960", "yesterday_price": 18100, "price": 18300, "today_start_price": 18100, "max_price": 23500, "min_price": 12700, "high_price": 18450, "low_price": 18100, "change": 1.1, "deal": 3815, "today_graph": "http://chart.finance.daum.net/time3/real/004960-290157.png?date=201610260935", "month_graph": "http://chart.finance.daum.net/candle3/004960-290157.png?date=201610260935", "three_month_graph": "http://chart.finance.daum.net/time3/3month/004960-290157.png?date=201610260935", "year_graph": "http://chart.finance.daum.net/time3/year/004960-290157.png?date=201610260935"}}, {"model": "stock.stock", "pk": 1823, "fields": {"business": "\uac74\uc124\uc5c5", "title": "\ud55c\uc804KPS", "code": "051600", "yesterday_price": 56700, "price": 56800, "today_start_price": 56200, "max_price": 73700, "min_price": 39700, "high_price": 57100, "low_price": 56100, "change": 0.18, "deal": 14282, "today_graph": "http://chart.finance.daum.net/time3/real/051600-290157.png?date=201610260935", "month_graph": "http://chart.finance.daum.net/candle3/051600-290157.png?date=201610260935", "three_month_graph": "http://chart.finance.daum.net/time3/3month/051600-290157.png?date=201610260935", "year_graph": "http://chart.finance.daum.net/time3/year/051600-290157.png?date=201610260935"}}, {"model": "stock.stock", "pk": 1824, "fields": {"business": "\uac74\uc124\uc5c5", "title": "\ud55c\uc9c4\uc911\uacf5\uc5c5", "code": "097230", "yesterday_price": 4045, "price": 3955, "today_start_price": 4010, "max_price": 5250, "min_price": 2835, "high_price": 4015, "low_price": 3925, "change": -2.22, "deal": 74776, "today_graph": "http://chart.finance.daum.net/time3/real/097230-290157.png?date=201610260935", "month_graph": "http://chart.finance.daum.net/candle3/097230-290157.png?date=201610260935", "three_month_graph": "http://chart.finance.daum.net/time3/3month/097230-290157.png?date=201610260935", "year_graph": "http://chart.finance.daum.net/time3/year/097230-290157.png?date=201610260935"}}, {"model": "stock.stock", "pk": 1825, "fields": {"business": "\uac74\uc124\uc5c5", "title": "\ud604\ub300\uac74\uc124", "code": "000720", "yesterday_price": 44400, "price": 43500, "today_start_price": 44100, "max_price": 57700, "min_price": 31100, "high_price": 44100, "low_price": 43400, "change": -2.03, "deal": 58942, "today_graph": "http://chart.finance.daum.net/time3/real/000720-290157.png?date=201610260935", "month_graph": "http://chart.finance.daum.net/candle3/000720-290157.png?date=201610260935", "three_month_graph": "http://chart.finance.daum.net/time3/3month/000720-290157.png?date=201610260935", "year_graph": "http://chart.finance.daum.net/time3/year/000720-290157.png?date=201610260935"}}, {"model": "stock.stock", "pk": 1826, "fields": {"business": "\uac74\uc124\uc5c5", "title": "\ud604\ub300\uac74\uc124\uc6b0", "code": "000725", "yesterday_price": 50900, "price": 50700, "today_start_price": 50100, "max_price": 66100, "min_price": 35700, "high_price": 50700, "low_price": 50100, "change": -0.39, "deal": 54, "today_graph": "http://chart.finance.daum.net/time3/real/000725-290157.png?date=201610260935", "month_graph": "http://chart.finance.daum.net/candle3/000725-290157.png?date=201610260935", "three_month_graph": "http://chart.finance.daum.net/time3/3month/000725-290157.png?date=201610260935", "year_graph": "http://chart.finance.daum.net/time3/year/000725-290157.png?date=201610260935"}}, {"model": "stock.stock", "pk": 1827, "fields": {"business": "\uac74\uc124\uc5c5", "title": "\ud604\ub300\uc0b0\uc5c5", "code": "012630", "yesterday_price": 51500, "price": 51800, "today_start_price": 51500, "max_price": 66900, "min_price": 36100, "high_price": 51900, "low_price": 50700, "change": 0.58, "deal": 32372, "today_graph": "http://chart.finance.daum.net/time3/real/012630-290157.png?date=201610260935", "month_graph": "http://chart.finance.daum.net/candle3/012630-290157.png?date=201610260935", "three_month_graph": "http://chart.finance.daum.net/time3/3month/012630-290157.png?date=201610260935", "year_graph": "http://chart.finance.daum.net/time3/year/012630-290157.png?date=201610260935"}}, {"model": "stock.stock", "pk": 1828, "fields": {"business": "\uac74\uc124\uc5c5", "title": "\ud654\uc131\uc0b0\uc5c5", "code": "002460", "yesterday_price": 13100, "price": 12900, "today_start_price": 13100, "max_price": 17000, "min_price": 9200, "high_price": 13150, "low_price": 12850, "change": -1.53, "deal": 3580, "today_graph": "http://chart.finance.daum.net/time3/real/002460-290157.png?date=201610260935", "month_graph": "http://chart.finance.daum.net/candle3/002460-290157.png?date=201610260935", "three_month_graph": "http://chart.finance.daum.net/time3/3month/002460-290157.png?date=201610260935", "year_graph": "http://chart.finance.daum.net/time3/year/002460-290157.png?date=201610260935"}}, {"model": "stock.stock", "pk": 1829, "fields": {"business": "\uae08\uc735\uc5c5", "title": "BNK\uae08\uc735\uc9c0\uc8fc", "code": "138930", "yesterday_price": 9670, "price": 9410, "today_start_price": 9600, "max_price": 12550, "min_price": 6770, "high_price": 9620, "low_price": 9370, "change": -2.69, "deal": 284176, "today_graph": "http://chart.finance.daum.net/time3/real/138930-290157.png?date=201610260935", "month_graph": "http://chart.finance.daum.net/candle3/138930-290157.png?date=201610260935", "three_month_graph": "http://chart.finance.daum.net/time3/3month/138930-290157.png?date=201610260935", "year_graph": "http://chart.finance.daum.net/time3/year/138930-290157.png?date=201610260935"}}, {"model": "stock.stock", "pk": 1830, "fields": {"business": "\uae08\uc735\uc5c5", "title": "DGB\uae08\uc735\uc9c0\uc8fc", "code": "139130", "yesterday_price": 9990, "price": 9820, "today_start_price": 9940, "max_price": 12950, "min_price": 7000, "high_price": 9970, "low_price": 9800, "change": -1.7, "deal": 94896, "today_graph": "http://chart.finance.daum.net/time3/real/139130-290157.png?date=201610260935", "month_graph": "http://chart.finance.daum.net/candle3/139130-290157.png?date=201610260935", "three_month_graph": "http://chart.finance.daum.net/time3/3month/139130-290157.png?date=201610260935", "year_graph": "http://chart.finance.daum.net/time3/year/139130-290157.png?date=201610260935"}}, {"model": "stock.stock", "pk": 1831, "fields": {"business": "\uae08\uc735\uc5c5", "title": "HMC\ud22c\uc790\uc99d\uad8c", "code": "001500", "yesterday_price": 9760, "price": 9690, "today_start_price": 9750, "max_price": 12650, "min_price": 6840, "high_price": 9750, "low_price": 9680, "change": -0.72, "deal": 2948, "today_graph": "http://chart.finance.daum.net/time3/real/001500-290157.png?date=201610260935", "month_graph": "http://chart.finance.daum.net/candle3/001500-290157.png?date=201610260935", "three_month_graph": "http://chart.finance.daum.net/time3/3month/001500-290157.png?date=201610260935", "year_graph": "http://chart.finance.daum.net/time3/year/001500-290157.png?date=201610260935"}}, {"model": "stock.stock", "pk": 1832, "fields": {"business": "\uae08\uc735\uc5c5", "title": "JB\uae08\uc735\uc9c0\uc8fc", "code": "175330", "yesterday_price": 6250, "price": 6210, "today_start_price": 6190, "max_price": 8120, "min_price": 4380, "high_price": 6240, "low_price": 6190, "change": -0.64, "deal": 18779, "today_graph": "http://chart.finance.daum.net/time3/real/175330-290157.png?date=201610260935", "month_graph": "http://chart.finance.daum.net/candle3/175330-290157.png?date=201610260935", "three_month_graph": "http://chart.finance.daum.net/time3/3month/175330-290157.png?date=201610260935", "year_graph": "http://chart.finance.daum.net/time3/year/175330-290157.png?date=201610260935"}}, {"model": "stock.stock", "pk": 1833, "fields": {"business": "\uae08\uc735\uc5c5", "title": "KB\uae08\uc735", "code": "105560", "yesterday_price": 43900, "price": 43050, "today_start_price": 43750, "max_price": 57000, "min_price": 30750, "high_price": 43800, "low_price": 43000, "change": -1.94, "deal": 134479, "today_graph": "http://chart.finance.daum.net/time3/real/105560-290157.png?date=201610260935", "month_graph": "http://chart.finance.daum.net/candle3/105560-290157.png?date=201610260935", "three_month_graph": "http://chart.finance.daum.net/time3/3month/105560-290157.png?date=201610260935", "year_graph": "http://chart.finance.daum.net/time3/year/105560-290157.png?date=201610260935"}}, {"model": "stock.stock", "pk": 1834, "fields": {"business": "\uae08\uc735\uc5c5", "title": "KB\uc190\ud574\ubcf4\ud5d8", "code": "002550", "yesterday_price": 28300, "price": 27900, "today_start_price": 28250, "max_price": 36750, "min_price": 19850, "high_price": 28250, "low_price": 27850, "change": -1.41, "deal": 17658, "today_graph": "http://chart.finance.daum.net/time3/real/002550-290157.png?date=201610260935", "month_graph": "http://chart.finance.daum.net/candle3/002550-290157.png?date=201610260935", "three_month_graph": "http://chart.finance.daum.net/time3/3month/002550-290157.png?date=201610260935", "year_graph": "http://chart.finance.daum.net/time3/year/002550-290157.png?date=201610260935"}}, {"model": "stock.stock", "pk": 1835, "fields": {"business": "\uae08\uc735\uc5c5", "title": "KTB\ud22c\uc790\uc99d\uad8c", "code": "030210", "yesterday_price": 3015, "price": 2935, "today_start_price": 2995, "max_price": 3915, "min_price": 2115, "high_price": 2995, "low_price": 2925, "change": -2.65, "deal": 49497, "today_graph": "http://chart.finance.daum.net/time3/real/030210-290157.png?date=201610260935", "month_graph": "http://chart.finance.daum.net/candle3/030210-290157.png?date=201610260935", "three_month_graph": "http://chart.finance.daum.net/time3/3month/030210-290157.png?date=201610260935", "year_graph": "http://chart.finance.daum.net/time3/year/030210-290157.png?date=201610260935"}}, {"model": "stock.stock", "pk": 1836, "fields": {"business": "\uae08\uc735\uc5c5", "title": "NH\ud22c\uc790\uc99d\uad8c", "code": "005940", "yesterday_price": 10450, "price": 10300, "today_start_price": 10350, "max_price": 13550, "min_price": 7350, "high_price": 10400, "low_price": 10300, "change": -1.44, "deal": 89533, "today_graph": "http://chart.finance.daum.net/time3/real/005940-290157.png?date=201610260935", "month_graph": "http://chart.finance.daum.net/candle3/005940-290157.png?date=201610260935", "three_month_graph": "http://chart.finance.daum.net/time3/3month/005940-290157.png?date=201610260935", "year_graph": "http://chart.finance.daum.net/time3/year/005940-290157.png?date=201610260935"}}, {"model": "stock.stock", "pk": 1837, "fields": {"business": "\uae08\uc735\uc5c5", "title": "NH\ud22c\uc790\uc99d\uad8c\uc6b0", "code": "005945", "yesterday_price": 7190, "price": 7140, "today_start_price": 7160, "max_price": 9340, "min_price": 5040, "high_price": 7170, "low_price": 7130, "change": -0.7, "deal": 724, "today_graph": "http://chart.finance.daum.net/time3/real/005945-290157.png?date=201610260935", "month_graph": "http://chart.finance.daum.net/candle3/005945-290157.png?date=201610260935", "three_month_graph": "http://chart.finance.daum.net/time3/3month/005945-290157.png?date=201610260935", "year_graph": "http://chart.finance.daum.net/time3/year/005945-290157.png?date=201610260935"}}, {"model": "stock.stock", "pk": 1838, "fields": {"business": "\uae08\uc735\uc5c5", "title": "SK\uc99d\uad8c", "code": "001510", "yesterday_price": 1110, "price": 1095, "today_start_price": 1100, "max_price": 1440, "min_price": 780, "high_price": 1110, "low_price": 1085, "change": -1.35, "deal": 831274, "today_graph": "http://chart.finance.daum.net/time3/real/001510-290157.png?date=201610260935", "month_graph": "http://chart.finance.daum.net/candle3/001510-290157.png?date=201610260935", "three_month_graph": "http://chart.finance.daum.net/time3/3month/001510-290157.png?date=201610260935", "year_graph": "http://chart.finance.daum.net/time3/year/001510-290157.png?date=201610260935"}}, {"model": "stock.stock", "pk": 1839, "fields": {"business": "\uae08\uc735\uc5c5", "title": "SK\uc99d\uad8c\uc6b0", "code": "001515", "yesterday_price": 1720, "price": 1710, "today_start_price": 1720, "max_price": 2235, "min_price": 1205, "high_price": 1720, "low_price": 1700, "change": -0.58, "deal": 9178, "today_graph": "http://chart.finance.daum.net/time3/real/001515-290157.png?date=201610260935", "month_graph": "http://chart.finance.daum.net/candle3/001515-290157.png?date=201610260935", "three_month_graph": "http://chart.finance.daum.net/time3/3month/001515-290157.png?date=201610260935", "year_graph": "http://chart.finance.daum.net/time3/year/001515-290157.png?date=201610260935"}}, {"model": "stock.stock", "pk": 1840, "fields": {"business": "\uae08\uc735\uc5c5", "title": "\uace8\ub4e0\ube0c\ub9bf\uc9c0\uc99d\uad8c", "code": "001290", "yesterday_price": 1000, "price": 997, "today_start_price": 997, "max_price": 1300, "min_price": 700, "high_price": 1000, "low_price": 991, "change": -0.3, "deal": 24965, "today_graph": "http://chart.finance.daum.net/time3/real/001290-290157.png?date=201610260935", "month_graph": "http://chart.finance.daum.net/candle3/001290-290157.png?date=201610260935", "three_month_graph": "http://chart.finance.daum.net/time3/3month/001290-290157.png?date=201610260935", "year_graph": "http://chart.finance.daum.net/time3/year/001290-290157.png?date=201610260935"}}, {"model": "stock.stock", "pk": 1841, "fields": {"business": "\uae08\uc735\uc5c5", "title": "\uad11\uc8fc\uc740\ud589", "code": "192530", "yesterday_price": 10350, "price": 10200, "today_start_price": 10400, "max_price": 13450, "min_price": 7250, "high_price": 10400, "low_price": 10200, "change": -1.45, "deal": 6261, "today_graph": "http://chart.finance.daum.net/time3/real/192530-290157.png?date=201610260935", "month_graph": "http://chart.finance.daum.net/candle3/192530-290157.png?date=201610260935", "three_month_graph": "http://chart.finance.daum.net/time3/3month/192530-290157.png?date=201610260935", "year_graph": "http://chart.finance.daum.net/time3/year/192530-290157.png?date=201610260935"}}, {"model": "stock.stock", "pk": 1842, "fields": {"business": "\uae08\uc735\uc5c5", "title": "\uad50\ubcf4\uc99d\uad8c", "code": "030610", "yesterday_price": 9330, "price": 9220, "today_start_price": 9360, "max_price": 12100, "min_price": 6540, "high_price": 9360, "low_price": 9200, "change": -1.18, "deal": 6231, "today_graph": "http://chart.finance.daum.net/time3/real/030610-290157.png?date=201610260935", "month_graph": "http://chart.finance.daum.net/candle3/030610-290157.png?date=201610260935", "three_month_graph": "http://chart.finance.daum.net/time3/3month/030610-290157.png?date=201610260935", "year_graph": "http://chart.finance.daum.net/time3/year/030610-290157.png?date=201610260935"}}, {"model": "stock.stock", "pk": 1843, "fields": {"business": "\uae08\uc735\uc5c5", "title": "\uae30\uc5c5\uc740\ud589", "code": "024110", "yesterday_price": 13400, "price": 13200, "today_start_price": 13350, "max_price": 17400, "min_price": 9400, "high_price": 13450, "low_price": 13200, "change": -1.49, "deal": 139219, "today_graph": "http://chart.finance.daum.net/time3/real/024110-290157.png?date=201610260936", "month_graph": "http://chart.finance.daum.net/candle3/024110-290157.png?date=201610260936", "three_month_graph": "http://chart.finance.daum.net/time3/3month/024110-290157.png?date=201610260936", "year_graph": "http://chart.finance.daum.net/time3/year/024110-290157.png?date=201610260936"}}, {"model": "stock.stock", "pk": 1844, "fields": {"business": "\uae08\uc735\uc5c5", "title": "\ub300\uc2e0\uc99d\uad8c", "code": "003540", "yesterday_price": 10850, "price": 10750, "today_start_price": 10950, "max_price": 14100, "min_price": 7600, "high_price": 10950, "low_price": 10750, "change": -0.92, "deal": 16989, "today_graph": "http://chart.finance.daum.net/time3/real/003540-290157.png?date=201610260936", "month_graph": "http://chart.finance.daum.net/candle3/003540-290157.png?date=201610260936", "three_month_graph": "http://chart.finance.daum.net/time3/3month/003540-290157.png?date=201610260936", "year_graph": "http://chart.finance.daum.net/time3/year/003540-290157.png?date=201610260936"}}, {"model": "stock.stock", "pk": 1845, "fields": {"business": "\uae08\uc735\uc5c5", "title": "\ub300\uc2e0\uc99d\uad8c2\uc6b0B", "code": "003547", "yesterday_price": 7320, "price": 7300, "today_start_price": 7320, "max_price": 9510, "min_price": 5130, "high_price": 7320, "low_price": 7300, "change": -0.27, "deal": 127, "today_graph": "http://chart.finance.daum.net/time3/real/003547-290157.png?date=201610260936", "month_graph": "http://chart.finance.daum.net/candle3/003547-290157.png?date=201610260936", "three_month_graph": "http://chart.finance.daum.net/time3/3month/003547-290157.png?date=201610260936", "year_graph": "http://chart.finance.daum.net/time3/year/003547-290157.png?date=201610260936"}}, {"model": "stock.stock", "pk": 1846, "fields": {"business": "\uae08\uc735\uc5c5", "title": "\ub300\uc2e0\uc99d\uad8c\uc6b0", "code": "003545", "yesterday_price": 7940, "price": 7870, "today_start_price": 7940, "max_price": 10300, "min_price": 5560, "high_price": 7940, "low_price": 7850, "change": -0.88, "deal": 4279, "today_graph": "http://chart.finance.daum.net/time3/real/003545-290157.png?date=201610260936", "month_graph": "http://chart.finance.daum.net/candle3/003545-290157.png?date=201610260936", "three_month_graph": "http://chart.finance.daum.net/time3/3month/003545-290157.png?date=201610260936", "year_graph": "http://chart.finance.daum.net/time3/year/003545-290157.png?date=201610260936"}}, {"model": "stock.stock", "pk": 1847, "fields": {"business": "\uae08\uc735\uc5c5", "title": "\ub3d9\ubd80\uc99d\uad8c", "code": "016610", "yesterday_price": 3450, "price": 3430, "today_start_price": 3460, "max_price": 4485, "min_price": 2415, "high_price": 3460, "low_price": 3415, "change": -0.58, "deal": 4437, "today_graph": "http://chart.finance.daum.net/time3/real/016610-290157.png?date=201610260936", "month_graph": "http://chart.finance.daum.net/candle3/016610-290157.png?date=201610260936", "three_month_graph": "http://chart.finance.daum.net/time3/3month/016610-290157.png?date=201610260936", "year_graph": "http://chart.finance.daum.net/time3/year/016610-290157.png?date=201610260936"}}, {"model": "stock.stock", "pk": 1848, "fields": {"business": "\uae08\uc735\uc5c5", "title": "\ub3d9\ubd80\ud654\uc7ac", "code": "005830", "yesterday_price": 70800, "price": 69800, "today_start_price": 70800, "max_price": 92000, "min_price": 49600, "high_price": 71000, "low_price": 69700, "change": -1.41, "deal": 7040, "today_graph": "http://chart.finance.daum.net/time3/real/005830-290157.png?date=201610260936", "month_graph": "http://chart.finance.daum.net/candle3/005830-290157.png?date=201610260936", "three_month_graph": "http://chart.finance.daum.net/time3/3month/005830-290157.png?date=201610260936", "year_graph": "http://chart.finance.daum.net/time3/year/005830-290157.png?date=201610260936"}}, {"model": "stock.stock", "pk": 1849, "fields": {"business": "\uae08\uc735\uc5c5", "title": "\ub3d9\uc591\uc0dd\uba85", "code": "082640", "yesterday_price": 12650, "price": 12700, "today_start_price": 12600, "max_price": 16400, "min_price": 8900, "high_price": 12750, "low_price": 12600, "change": 0.4, "deal": 5329, "today_graph": "http://chart.finance.daum.net/time3/real/082640-290157.png?date=201610260936", "month_graph": "http://chart.finance.daum.net/candle3/082640-290157.png?date=201610260936", "three_month_graph": "http://chart.finance.daum.net/time3/3month/082640-290157.png?date=201610260936", "year_graph": "http://chart.finance.daum.net/time3/year/082640-290157.png?date=201610260936"}}, {"model": "stock.stock", "pk": 1850, "fields": {"business": "\uae08\uc735\uc5c5", "title": "\ub86f\ub370\uc190\ud574\ubcf4\ud5d8", "code": "000400", "yesterday_price": 2715, "price": 2705, "today_start_price": 2715, "max_price": 3525, "min_price": 1905, "high_price": 2715, "low_price": 2695, "change": -0.37, "deal": 51276, "today_graph": "http://chart.finance.daum.net/time3/real/000400-290157.png?date=201610260936", "month_graph": "http://chart.finance.daum.net/candle3/000400-290157.png?date=201610260936", "three_month_graph": "http://chart.finance.daum.net/time3/3month/000400-290157.png?date=201610260936", "year_graph": "http://chart.finance.daum.net/time3/year/000400-290157.png?date=201610260936"}}, {"model": "stock.stock", "pk": 1851, "fields": {"business": "\uae08\uc735\uc5c5", "title": "\ub9e5\ucffc\ub9ac\uc778\ud504\ub77c", "code": "088980", "yesterday_price": 8810, "price": 8810, "today_start_price": 8810, "max_price": 11450, "min_price": 6170, "high_price": 8830, "low_price": 8810, "change": 0.0, "deal": 126085, "today_graph": "http://chart.finance.daum.net/time3/real/088980-290157.png?date=201610260936", "month_graph": "http://chart.finance.daum.net/candle3/088980-290157.png?date=201610260936", "three_month_graph": "http://chart.finance.daum.net/time3/3month/088980-290157.png?date=201610260936", "year_graph": "http://chart.finance.daum.net/time3/year/088980-290157.png?date=201610260936"}}, {"model": "stock.stock", "pk": 1852, "fields": {"business": "\uae08\uc735\uc5c5", "title": "\uba54\ub9ac\uce20\uae08\uc735\uc9c0\uc8fc", "code": "138040", "yesterday_price": 11500, "price": 11500, "today_start_price": 11500, "max_price": 14950, "min_price": 8050, "high_price": 11550, "low_price": 11450, "change": 0.0, "deal": 2692, "today_graph": "http://chart.finance.daum.net/time3/real/138040-290157.png?date=201610260936", "month_graph": "http://chart.finance.daum.net/candle3/138040-290157.png?date=201610260936", "three_month_graph": "http://chart.finance.daum.net/time3/3month/138040-290157.png?date=201610260936", "year_graph": "http://chart.finance.daum.net/time3/year/138040-290157.png?date=201610260936"}}, {"model": "stock.stock", "pk": 1853, "fields": {"business": "\uae08\uc735\uc5c5", "title": "\uba54\ub9ac\uce20\uc885\uae08\uc99d\uad8c", "code": "008560", "yesterday_price": 3405, "price": 3395, "today_start_price": 3405, "max_price": 4425, "min_price": 2385, "high_price": 3415, "low_price": 3385, "change": -0.29, "deal": 209308, "today_graph": "http://chart.finance.daum.net/time3/real/008560-290157.png?date=201610260936", "month_graph": "http://chart.finance.daum.net/candle3/008560-290157.png?date=201610260936", "three_month_graph": "http://chart.finance.daum.net/time3/3month/008560-290157.png?date=201610260936", "year_graph": "http://chart.finance.daum.net/time3/year/008560-290157.png?date=201610260936"}}, {"model": "stock.stock", "pk": 1854, "fields": {"business": "\uae08\uc735\uc5c5", "title": "\uba54\ub9ac\uce20\ud654\uc7ac", "code": "000060", "yesterday_price": 15750, "price": 15700, "today_start_price": 15750, "max_price": 20450, "min_price": 11050, "high_price": 15750, "low_price": 15650, "change": -0.32, "deal": 4803, "today_graph": "http://chart.finance.daum.net/time3/real/000060-290157.png?date=201610260936", "month_graph": "http://chart.finance.daum.net/candle3/000060-290157.png?date=201610260936", "three_month_graph": "http://chart.finance.daum.net/time3/3month/000060-290157.png?date=201610260936", "year_graph": "http://chart.finance.daum.net/time3/year/000060-290157.png?date=201610260936"}}, {"model": "stock.stock", "pk": 1855, "fields": {"business": "\uae08\uc735\uc5c5", "title": "\ubbf8\ub798\uc5d0\uc14b\ub300\uc6b0", "code": "006800", "yesterday_price": 7950, "price": 7870, "today_start_price": 7980, "max_price": 10300, "min_price": 5570, "high_price": 7980, "low_price": 7840, "change": -1.01, "deal": 241823, "today_graph": "http://chart.finance.daum.net/time3/real/006800-290157.png?date=201610260936", "month_graph": "http://chart.finance.daum.net/candle3/006800-290157.png?date=201610260936", "three_month_graph": "http://chart.finance.daum.net/time3/3month/006800-290157.png?date=201610260936", "year_graph": "http://chart.finance.daum.net/time3/year/006800-290157.png?date=201610260936"}}, {"model": "stock.stock", "pk": 1856, "fields": {"business": "\uae08\uc735\uc5c5", "title": "\ubbf8\ub798\uc5d0\uc14b\ub300\uc6b0\uc6b0", "code": "006805", "yesterday_price": 5780, "price": 5780, "today_start_price": 5800, "max_price": 7510, "min_price": 4050, "high_price": 5800, "low_price": 5780, "change": 0.0, "deal": 94, "today_graph": "http://chart.finance.daum.net/time3/real/006805-290157.png?date=201610260936", "month_graph": "http://chart.finance.daum.net/candle3/006805-290157.png?date=201610260936", "three_month_graph": "http://chart.finance.daum.net/time3/3month/006805-290157.png?date=201610260936", "year_graph": "http://chart.finance.daum.net/time3/year/006805-290157.png?date=201610260936"}}, {"model": "stock.stock", "pk": 1857, "fields": {"business": "\uae08\uc735\uc5c5", "title": "\ubbf8\ub798\uc5d0\uc14b\uc0dd\uba85", "code": "085620", "yesterday_price": 4625, "price": 4595, "today_start_price": 4630, "max_price": 6010, "min_price": 3240, "high_price": 4660, "low_price": 4590, "change": -0.65, "deal": 48066, "today_graph": "http://chart.finance.daum.net/time3/real/085620-290157.png?date=201610260936", "month_graph": "http://chart.finance.daum.net/candle3/085620-290157.png?date=201610260936", "three_month_graph": "http://chart.finance.daum.net/time3/3month/085620-290157.png?date=201610260936", "year_graph": "http://chart.finance.daum.net/time3/year/085620-290157.png?date=201610260936"}}, {"model": "stock.stock", "pk": 1858, "fields": {"business": "\uae08\uc735\uc5c5", "title": "\ubbf8\ub798\uc5d0\uc14b\uc99d\uad8c", "code": "037620", "yesterday_price": 23200, "price": 22950, "today_start_price": 23100, "max_price": 30150, "min_price": 16250, "high_price": 23200, "low_price": 22850, "change": -1.08, "deal": 38160, "today_graph": "http://chart.finance.daum.net/time3/real/037620-290157.png?date=201610260936", "month_graph": "http://chart.finance.daum.net/candle3/037620-290157.png?date=201610260936", "three_month_graph": "http://chart.finance.daum.net/time3/3month/037620-290157.png?date=201610260936", "year_graph": "http://chart.finance.daum.net/time3/year/037620-290157.png?date=201610260936"}}, {"model": "stock.stock", "pk": 1859, "fields": {"business": "\uae08\uc735\uc5c5", "title": "\ubd80\uad6d\uc99d\uad8c", "code": "001270", "yesterday_price": 20300, "price": 20300, "today_start_price": 20300, "max_price": 26350, "min_price": 14250, "high_price": 20300, "low_price": 20300, "change": 0.0, "deal": 2, "today_graph": "http://chart.finance.daum.net/time3/real/001270-290157.png?date=201610260936", "month_graph": "http://chart.finance.daum.net/candle3/001270-290157.png?date=201610260936", "three_month_graph": "http://chart.finance.daum.net/time3/3month/001270-290157.png?date=201610260936", "year_graph": "http://chart.finance.daum.net/time3/year/001270-290157.png?date=201610260936"}}, {"model": "stock.stock", "pk": 1860, "fields": {"business": "\uae08\uc735\uc5c5", "title": "\ubd80\uad6d\uc99d\uad8c\uc6b0", "code": "001275", "yesterday_price": 19950, "price": 19950, "today_start_price": 0, "max_price": 25900, "min_price": 14000, "high_price": 0, "low_price": 0, "change": 0.0, "deal": 0, "today_graph": "http://chart.finance.daum.net/time3/real/001275-290157.png?date=201610260936", "month_graph": "http://chart.finance.daum.net/candle3/001275-290157.png?date=201610260936", "three_month_graph": "http://chart.finance.daum.net/time3/3month/001275-290157.png?date=201610260936", "year_graph": "http://chart.finance.daum.net/time3/year/001275-290157.png?date=201610260936"}}, {"model": "stock.stock", "pk": 1861, "fields": {"business": "\uae08\uc735\uc5c5", "title": "\uc0bc\uc131\uc0dd\uba85", "code": "032830", "yesterday_price": 111500, "price": 109000, "today_start_price": 111000, "max_price": 144500, "min_price": 78500, "high_price": 111500, "low_price": 108500, "change": -2.24, "deal": 51046, "today_graph": "http://chart.finance.daum.net/time3/real/032830-290157.png?date=201610260936", "month_graph": "http://chart.finance.daum.net/candle3/032830-290157.png?date=201610260936", "three_month_graph": "http://chart.finance.daum.net/time3/3month/032830-290157.png?date=201610260936", "year_graph": "http://chart.finance.daum.net/time3/year/032830-290157.png?date=201610260936"}}, {"model": "stock.stock", "pk": 1862, "fields": {"business": "\uae08\uc735\uc5c5", "title": "\uc0bc\uc131\uc99d\uad8c", "code": "016360", "yesterday_price": 35650, "price": 35400, "today_start_price": 35750, "max_price": 46300, "min_price": 25000, "high_price": 35750, "low_price": 35350, "change": -0.7, "deal": 38983, "today_graph": "http://chart.finance.daum.net/time3/real/016360-290157.png?date=201610260936", "month_graph": "http://chart.finance.daum.net/candle3/016360-290157.png?date=201610260936", "three_month_graph": "http://chart.finance.daum.net/time3/3month/016360-290157.png?date=201610260936", "year_graph": "http://chart.finance.daum.net/time3/year/016360-290157.png?date=201610260936"}}, {"model": "stock.stock", "pk": 1863, "fields": {"business": "\uae08\uc735\uc5c5", "title": "\uc0bc\uc131\uce74\ub4dc", "code": "029780", "yesterday_price": 50000, "price": 49300, "today_start_price": 50000, "max_price": 65000, "min_price": 35000, "high_price": 50100, "low_price": 49000, "change": -1.4, "deal": 8058, "today_graph": "http://chart.finance.daum.net/time3/real/029780-290157.png?date=201610260936", "month_graph": "http://chart.finance.daum.net/candle3/029780-290157.png?date=201610260936", "three_month_graph": "http://chart.finance.daum.net/time3/3month/029780-290157.png?date=201610260936", "year_graph": "http://chart.finance.daum.net/time3/year/029780-290157.png?date=201610260936"}}, {"model": "stock.stock", "pk": 1864, "fields": {"business": "\uae08\uc735\uc5c5", "title": "\uc0bc\uc131\ud654\uc7ac", "code": "000810", "yesterday_price": 294500, "price": 292500, "today_start_price": 294000, "max_price": 382500, "min_price": 206500, "high_price": 294500, "low_price": 292000, "change": -0.68, "deal": 4943, "today_graph": "http://chart.finance.daum.net/time3/real/000810-290157.png?date=201610260936", "month_graph": "http://chart.finance.daum.net/candle3/000810-290157.png?date=201610260936", "three_month_graph": "http://chart.finance.daum.net/time3/3month/000810-290157.png?date=201610260936", "year_graph": "http://chart.finance.daum.net/time3/year/000810-290157.png?date=201610260936"}}, {"model": "stock.stock", "pk": 1865, "fields": {"business": "\uae08\uc735\uc5c5", "title": "\uc0bc\uc131\ud654\uc7ac\uc6b0", "code": "000815", "yesterday_price": 189500, "price": 188000, "today_start_price": 188000, "max_price": 246000, "min_price": 133000, "high_price": 188000, "low_price": 188000, "change": -0.79, "deal": 18, "today_graph": "http://chart.finance.daum.net/time3/real/000815-290157.png?date=201610260936", "month_graph": "http://chart.finance.daum.net/candle3/000815-290157.png?date=201610260936", "three_month_graph": "http://chart.finance.daum.net/time3/3month/000815-290157.png?date=201610260936", "year_graph": "http://chart.finance.daum.net/time3/year/000815-290157.png?date=201610260936"}}, {"model": "stock.stock", "pk": 1866, "fields": {"business": "\uae08\uc735\uc5c5", "title": "\uc2e0\uc601\uc99d\uad8c", "code": "001720", "yesterday_price": 50200, "price": 50400, "today_start_price": 50500, "max_price": 65200, "min_price": 35200, "high_price": 50500, "low_price": 50300, "change": 0.4, "deal": 16, "today_graph": "http://chart.finance.daum.net/time3/real/001720-290157.png?date=201610260936", "month_graph": "http://chart.finance.daum.net/candle3/001720-290157.png?date=201610260936", "three_month_graph": "http://chart.finance.daum.net/time3/3month/001720-290157.png?date=201610260936", "year_graph": "http://chart.finance.daum.net/time3/year/001720-290157.png?date=201610260936"}}, {"model": "stock.stock", "pk": 1867, "fields": {"business": "\uae08\uc735\uc5c5", "title": "\uc2e0\uc601\uc99d\uad8c\uc6b0", "code": "001725", "yesterday_price": 46750, "price": 46750, "today_start_price": 46750, "max_price": 60700, "min_price": 32750, "high_price": 46750, "low_price": 46750, "change": 0.0, "deal": 4, "today_graph": "http://chart.finance.daum.net/time3/real/001725-290157.png?date=201610260936", "month_graph": "http://chart.finance.daum.net/candle3/001725-290157.png?date=201610260936", "three_month_graph": "http://chart.finance.daum.net/time3/3month/001725-290157.png?date=201610260936", "year_graph": "http://chart.finance.daum.net/time3/year/001725-290157.png?date=201610260936"}}, {"model": "stock.stock", "pk": 1868, "fields": {"business": "\uae08\uc735\uc5c5", "title": "\uc2e0\ud55c\uc9c0\uc8fc", "code": "055550", "yesterday_price": 44150, "price": 43400, "today_start_price": 44000, "max_price": 57300, "min_price": 30950, "high_price": 44000, "low_price": 43400, "change": -1.7, "deal": 134095, "today_graph": "http://chart.finance.daum.net/time3/real/055550-290157.png?date=201610260936", "month_graph": "http://chart.finance.daum.net/candle3/055550-290157.png?date=201610260936", "three_month_graph": "http://chart.finance.daum.net/time3/3month/055550-290157.png?date=201610260936", "year_graph": "http://chart.finance.daum.net/time3/year/055550-290157.png?date=201610260936"}}, {"model": "stock.stock", "pk": 1869, "fields": {"business": "\uae08\uc735\uc5c5", "title": "\uc544\uc8fc\uce90\ud53c\ud0c8", "code": "033660", "yesterday_price": 7080, "price": 7040, "today_start_price": 7080, "max_price": 9200, "min_price": 4960, "high_price": 7080, "low_price": 7030, "change": -0.56, "deal": 1192, "today_graph": "http://chart.finance.daum.net/time3/real/033660-290157.png?date=201610260936", "month_graph": "http://chart.finance.daum.net/candle3/033660-290157.png?date=201610260936", "three_month_graph": "http://chart.finance.daum.net/time3/3month/033660-290157.png?date=201610260936", "year_graph": "http://chart.finance.daum.net/time3/year/033660-290157.png?date=201610260936"}}, {"model": "stock.stock", "pk": 1870, "fields": {"business": "\uae08\uc735\uc5c5", "title": "\uc6b0\ub9ac\uc740\ud589", "code": "000030", "yesterday_price": 12800, "price": 12650, "today_start_price": 12750, "max_price": 16600, "min_price": 9000, "high_price": 12800, "low_price": 12600, "change": -1.17, "deal": 242870, "today_graph": "http://chart.finance.daum.net/time3/real/000030-290157.png?date=201610260936", "month_graph": "http://chart.finance.daum.net/candle3/000030-290157.png?date=201610260936", "three_month_graph": "http://chart.finance.daum.net/time3/3month/000030-290157.png?date=201610260936", "year_graph": "http://chart.finance.daum.net/time3/year/000030-290157.png?date=201610260936"}}, {"model": "stock.stock", "pk": 1871, "fields": {"business": "\uae08\uc735\uc5c5", "title": "\uc6b0\ub9ac\uc885\uae08", "code": "010050", "yesterday_price": 713, "price": 706, "today_start_price": 712, "max_price": 926, "min_price": 500, "high_price": 713, "low_price": 703, "change": -0.98, "deal": 488370, "today_graph": "http://chart.finance.daum.net/time3/real/010050-290157.png?date=201610260936", "month_graph": "http://chart.finance.daum.net/candle3/010050-290157.png?date=201610260936", "three_month_graph": "http://chart.finance.daum.net/time3/3month/010050-290157.png?date=201610260936", "year_graph": "http://chart.finance.daum.net/time3/year/010050-290157.png?date=201610260936"}}, {"model": "stock.stock", "pk": 1872, "fields": {"business": "\uae08\uc735\uc5c5", "title": "\uc720\uc548\ud0c0\uc99d\uad8c", "code": "003470", "yesterday_price": 3390, "price": 3335, "today_start_price": 3385, "max_price": 4405, "min_price": 2375, "high_price": 3385, "low_price": 3330, "change": -1.62, "deal": 87657, "today_graph": "http://chart.finance.daum.net/time3/real/003470-290157.png?date=201610260936", "month_graph": "http://chart.finance.daum.net/candle3/003470-290157.png?date=201610260936", "three_month_graph": "http://chart.finance.daum.net/time3/3month/003470-290157.png?date=201610260936", "year_graph": "http://chart.finance.daum.net/time3/year/003470-290157.png?date=201610260936"}}, {"model": "stock.stock", "pk": 1873, "fields": {"business": "\uae08\uc735\uc5c5", "title": "\uc720\uc548\ud0c0\uc99d\uad8c\uc6b0", "code": "003475", "yesterday_price": 2185, "price": 2175, "today_start_price": 2150, "max_price": 2840, "min_price": 1530, "high_price": 2205, "low_price": 2150, "change": -0.46, "deal": 905, "today_graph": "http://chart.finance.daum.net/time3/real/003475-290157.png?date=201610260936", "month_graph": "http://chart.finance.daum.net/candle3/003475-290157.png?date=201610260936", "three_month_graph": "http://chart.finance.daum.net/time3/3month/003475-290157.png?date=201610260936", "year_graph": "http://chart.finance.daum.net/time3/year/003475-290157.png?date=201610260936"}}, {"model": "stock.stock", "pk": 1874, "fields": {"business": "\uae08\uc735\uc5c5", "title": "\uc720\uc9c4\ud22c\uc790\uc99d\uad8c", "code": "001200", "yesterday_price": 2630, "price": 2585, "today_start_price": 2630, "max_price": 3415, "min_price": 1845, "high_price": 2630, "low_price": 2575, "change": -1.71, "deal": 51204, "today_graph": "http://chart.finance.daum.net/time3/real/001200-290157.png?date=201610260936", "month_graph": "http://chart.finance.daum.net/candle3/001200-290157.png?date=201610260936", "three_month_graph": "http://chart.finance.daum.net/time3/3month/001200-290157.png?date=201610260936", "year_graph": "http://chart.finance.daum.net/time3/year/001200-290157.png?date=201610260936"}}, {"model": "stock.stock", "pk": 1875, "fields": {"business": "\uae08\uc735\uc5c5", "title": "\uc720\ud654\uc99d\uad8c", "code": "003460", "yesterday_price": 15850, "price": 15850, "today_start_price": 0, "max_price": 20600, "min_price": 11100, "high_price": 0, "low_price": 0, "change": 0.0, "deal": 0, "today_graph": "http://chart.finance.daum.net/time3/real/003460-290157.png?date=201610260936", "month_graph": "http://chart.finance.daum.net/candle3/003460-290157.png?date=201610260936", "three_month_graph": "http://chart.finance.daum.net/time3/3month/003460-290157.png?date=201610260936", "year_graph": "http://chart.finance.daum.net/time3/year/003460-290157.png?date=201610260936"}}, {"model": "stock.stock", "pk": 1876, "fields": {"business": "\uae08\uc735\uc5c5", "title": "\uc720\ud654\uc99d\uad8c\uc6b0", "code": "003465", "yesterday_price": 14900, "price": 14950, "today_start_price": 15250, "max_price": 19350, "min_price": 10450, "high_price": 15250, "low_price": 14900, "change": 0.34, "deal": 15, "today_graph": "http://chart.finance.daum.net/time3/real/003465-290157.png?date=201610260936", "month_graph": "http://chart.finance.daum.net/candle3/003465-290157.png?date=201610260936", "three_month_graph": "http://chart.finance.daum.net/time3/3month/003465-290157.png?date=201610260936", "year_graph": "http://chart.finance.daum.net/time3/year/003465-290157.png?date=201610260936"}}, {"model": "stock.stock", "pk": 1877, "fields": {"business": "\uae08\uc735\uc5c5", "title": "\uc81c\uc8fc\uc740\ud589", "code": "006220", "yesterday_price": 8230, "price": 8060, "today_start_price": 8200, "max_price": 10650, "min_price": 5770, "high_price": 8220, "low_price": 8060, "change": -2.07, "deal": 5916, "today_graph": "http://chart.finance.daum.net/time3/real/006220-290157.png?date=201610260936", "month_graph": "http://chart.finance.daum.net/candle3/006220-290157.png?date=201610260936", "three_month_graph": "http://chart.finance.daum.net/time3/3month/006220-290157.png?date=201610260936", "year_graph": "http://chart.finance.daum.net/time3/year/006220-290157.png?date=201610260936"}}, {"model": "stock.stock", "pk": 1878, "fields": {"business": "\uae08\uc735\uc5c5", "title": "\ucf00\uc774\ube44\uce90\ud53c\ud0c8", "code": "021960", "yesterday_price": 25450, "price": 25600, "today_start_price": 25700, "max_price": 33050, "min_price": 17850, "high_price": 25700, "low_price": 25400, "change": 0.59, "deal": 752, "today_graph": "http://chart.finance.daum.net/time3/real/021960-290157.png?date=201610260936", "month_graph": "http://chart.finance.daum.net/candle3/021960-290157.png?date=201610260936", "three_month_graph": "http://chart.finance.daum.net/time3/3month/021960-290157.png?date=201610260936", "year_graph": "http://chart.finance.daum.net/time3/year/021960-290157.png?date=201610260936"}}, {"model": "stock.stock", "pk": 1879, "fields": {"business": "\uae08\uc735\uc5c5", "title": "\ucf54\ub9ac\uc548\ub9ac", "code": "003690", "yesterday_price": 11950, "price": 11900, "today_start_price": 11950, "max_price": 15500, "min_price": 8400, "high_price": 11950, "low_price": 11850, "change": -0.42, "deal": 7006, "today_graph": "http://chart.finance.daum.net/time3/real/003690-290157.png?date=201610260936", "month_graph": "http://chart.finance.daum.net/candle3/003690-290157.png?date=201610260936", "three_month_graph": "http://chart.finance.daum.net/time3/3month/003690-290157.png?date=201610260936", "year_graph": "http://chart.finance.daum.net/time3/year/003690-290157.png?date=201610260936"}}, {"model": "stock.stock", "pk": 1880, "fields": {"business": "\uae08\uc735\uc5c5", "title": "\ud0a4\uc6c0\uc99d\uad8c", "code": "039490", "yesterday_price": 68000, "price": 68400, "today_start_price": 68600, "max_price": 88400, "min_price": 47600, "high_price": 68700, "low_price": 68000, "change": 0.59, "deal": 1412, "today_graph": "http://chart.finance.daum.net/time3/real/039490-290157.png?date=201610260936", "month_graph": "http://chart.finance.daum.net/candle3/039490-290157.png?date=201610260936", "three_month_graph": "http://chart.finance.daum.net/time3/3month/039490-290157.png?date=201610260936", "year_graph": "http://chart.finance.daum.net/time3/year/039490-290157.png?date=201610260936"}}, {"model": "stock.stock", "pk": 1881, "fields": {"business": "\uae08\uc735\uc5c5", "title": "\ud558\ub098\uae08\uc735\uc9c0\uc8fc", "code": "086790", "yesterday_price": 33100, "price": 32500, "today_start_price": 33200, "max_price": 43000, "min_price": 23200, "high_price": 33250, "low_price": 32500, "change": -1.81, "deal": 166665, "today_graph": "http://chart.finance.daum.net/time3/real/086790-290157.png?date=201610260936", "month_graph": "http://chart.finance.daum.net/candle3/086790-290157.png?date=201610260936", "three_month_graph": "http://chart.finance.daum.net/time3/3month/086790-290157.png?date=201610260936", "year_graph": "http://chart.finance.daum.net/time3/year/086790-290157.png?date=201610260936"}}, {"model": "stock.stock", "pk": 1882, "fields": {"business": "\uae08\uc735\uc5c5", "title": "\ud55c\uad6d\uae08\uc735\uc9c0\uc8fc", "code": "071050", "yesterday_price": 41800, "price": 41300, "today_start_price": 41800, "max_price": 54300, "min_price": 29300, "high_price": 41850, "low_price": 41250, "change": -1.2, "deal": 7663, "today_graph": "http://chart.finance.daum.net/time3/real/071050-290157.png?date=201610260936", "month_graph": "http://chart.finance.daum.net/candle3/071050-290157.png?date=201610260936", "three_month_graph": "http://chart.finance.daum.net/time3/3month/071050-290157.png?date=201610260936", "year_graph": "http://chart.finance.daum.net/time3/year/071050-290157.png?date=201610260936"}}, {"model": "stock.stock", "pk": 1883, "fields": {"business": "\uae08\uc735\uc5c5", "title": "\ud55c\uad6d\uae08\uc735\uc9c0\uc8fc\uc6b0", "code": "071055", "yesterday_price": 23300, "price": 23250, "today_start_price": 23400, "max_price": 30250, "min_price": 16350, "high_price": 23400, "low_price": 23200, "change": -0.21, "deal": 263, "today_graph": "http://chart.finance.daum.net/time3/real/071055-290157.png?date=201610260936", "month_graph": "http://chart.finance.daum.net/candle3/071055-290157.png?date=201610260936", "three_month_graph": "http://chart.finance.daum.net/time3/3month/071055-290157.png?date=201610260936", "year_graph": "http://chart.finance.daum.net/time3/year/071055-290157.png?date=201610260936"}}, {"model": "stock.stock", "pk": 1884, "fields": {"business": "\uae08\uc735\uc5c5", "title": "\ud55c\uad6d\uc790\uc0b0\uc2e0\ud0c1", "code": "123890", "yesterday_price": 8280, "price": 8100, "today_start_price": 8160, "max_price": 10750, "min_price": 5800, "high_price": 8320, "low_price": 8090, "change": -2.17, "deal": 12837, "today_graph": "http://chart.finance.daum.net/time3/real/123890-290157.png?date=201610260936", "month_graph": "http://chart.finance.daum.net/candle3/123890-290157.png?date=201610260936", "three_month_graph": "http://chart.finance.daum.net/time3/3month/123890-290157.png?date=201610260936", "year_graph": "http://chart.finance.daum.net/time3/year/123890-290157.png?date=201610260936"}}, {"model": "stock.stock", "pk": 1885, "fields": {"business": "\uae08\uc735\uc5c5", "title": "\ud55c\uad6d\ud1a0\uc9c0\uc2e0\ud0c1", "code": "034830", "yesterday_price": 3180, "price": 3140, "today_start_price": 3180, "max_price": 4130, "min_price": 2230, "high_price": 3180, "low_price": 3130, "change": -1.26, "deal": 64420, "today_graph": "http://chart.finance.daum.net/time3/real/034830-290157.png?date=201610260936", "month_graph": "http://chart.finance.daum.net/candle3/034830-290157.png?date=201610260936", "three_month_graph": "http://chart.finance.daum.net/time3/3month/034830-290157.png?date=201610260936", "year_graph": "http://chart.finance.daum.net/time3/year/034830-290157.png?date=201610260936"}}, {"model": "stock.stock", "pk": 1886, "fields": {"business": "\uae08\uc735\uc5c5", "title": "\ud55c\uc591\uc99d\uad8c", "code": "001750", "yesterday_price": 7520, "price": 7500, "today_start_price": 7500, "max_price": 9770, "min_price": 5270, "high_price": 7500, "low_price": 7470, "change": -0.27, "deal": 1890, "today_graph": "http://chart.finance.daum.net/time3/real/001750-290157.png?date=201610260936", "month_graph": "http://chart.finance.daum.net/candle3/001750-290157.png?date=201610260936", "three_month_graph": "http://chart.finance.daum.net/time3/3month/001750-290157.png?date=201610260936", "year_graph": "http://chart.finance.daum.net/time3/year/001750-290157.png?date=201610260936"}}, {"model": "stock.stock", "pk": 1887, "fields": {"business": "\uae08\uc735\uc5c5", "title": "\ud55c\uc591\uc99d\uad8c\uc6b0", "code": "001755", "yesterday_price": 7900, "price": 7830, "today_start_price": 7720, "max_price": 10250, "min_price": 5530, "high_price": 7830, "low_price": 7720, "change": -0.89, "deal": 29, "today_graph": "http://chart.finance.daum.net/time3/real/001755-290157.png?date=201610260936", "month_graph": "http://chart.finance.daum.net/candle3/001755-290157.png?date=201610260936", "three_month_graph": "http://chart.finance.daum.net/time3/3month/001755-290157.png?date=201610260936", "year_graph": "http://chart.finance.daum.net/time3/year/001755-290157.png?date=201610260936"}}, {"model": "stock.stock", "pk": 1888, "fields": {"business": "\uae08\uc735\uc5c5", "title": "\ud55c\ud654\uc0dd\uba85", "code": "088350", "yesterday_price": 6450, "price": 6280, "today_start_price": 6380, "max_price": 8380, "min_price": 4520, "high_price": 6440, "low_price": 6240, "change": -2.64, "deal": 192596, "today_graph": "http://chart.finance.daum.net/time3/real/088350-290157.png?date=201610260936", "month_graph": "http://chart.finance.daum.net/candle3/088350-290157.png?date=201610260936", "three_month_graph": "http://chart.finance.daum.net/time3/3month/088350-290157.png?date=201610260936", "year_graph": "http://chart.finance.daum.net/time3/year/088350-290157.png?date=201610260936"}}, {"model": "stock.stock", "pk": 1889, "fields": {"business": "\uae08\uc735\uc5c5", "title": "\ud55c\ud654\uc190\ud574\ubcf4\ud5d8", "code": "000370", "yesterday_price": 7420, "price": 7360, "today_start_price": 7320, "max_price": 9640, "min_price": 5200, "high_price": 7410, "low_price": 7310, "change": -0.81, "deal": 30114, "today_graph": "http://chart.finance.daum.net/time3/real/000370-290157.png?date=201610260936", "month_graph": "http://chart.finance.daum.net/candle3/000370-290157.png?date=201610260936", "three_month_graph": "http://chart.finance.daum.net/time3/3month/000370-290157.png?date=201610260936", "year_graph": "http://chart.finance.daum.net/time3/year/000370-290157.png?date=201610260936"}}, {"model": "stock.stock", "pk": 1890, "fields": {"business": "\uae08\uc735\uc5c5", "title": "\ud55c\ud654\ud22c\uc790\uc99d\uad8c", "code": "003530", "yesterday_price": 2300, "price": 2285, "today_start_price": 2295, "max_price": 2990, "min_price": 1610, "high_price": 2295, "low_price": 2280, "change": -0.65, "deal": 78315, "today_graph": "http://chart.finance.daum.net/time3/real/003530-290157.png?date=201610260936", "month_graph": "http://chart.finance.daum.net/candle3/003530-290157.png?date=201610260936", "three_month_graph": "http://chart.finance.daum.net/time3/3month/003530-290157.png?date=201610260936", "year_graph": "http://chart.finance.daum.net/time3/year/003530-290157.png?date=201610260936"}}, {"model": "stock.stock", "pk": 1891, "fields": {"business": "\uae08\uc735\uc5c5", "title": "\ud55c\ud654\ud22c\uc790\uc99d\uad8c\uc6b0", "code": "003535", "yesterday_price": 2030, "price": 2045, "today_start_price": 2045, "max_price": 2635, "min_price": 1425, "high_price": 2045, "low_price": 2045, "change": 0.74, "deal": 10, "today_graph": "http://chart.finance.daum.net/time3/real/003535-290157.png?date=201610260936", "month_graph": "http://chart.finance.daum.net/candle3/003535-290157.png?date=201610260936", "three_month_graph": "http://chart.finance.daum.net/time3/3month/003535-290157.png?date=201610260936", "year_graph": "http://chart.finance.daum.net/time3/year/003535-290157.png?date=201610260936"}}, {"model": "stock.stock", "pk": 1892, "fields": {"business": "\uae08\uc735\uc5c5", "title": "\ud604\ub300\uc99d\uad8c", "code": "003450", "yesterday_price": 7370, "price": 7370, "today_start_price": 0, "max_price": 9580, "min_price": 5160, "high_price": 0, "low_price": 0, "change": 0.0, "deal": 0, "today_graph": "http://chart.finance.daum.net/time3/real/003450-290157.png?date=201610260936", "month_graph": "http://chart.finance.daum.net/candle3/003450-290157.png?date=201610260936", "three_month_graph": "http://chart.finance.daum.net/time3/3month/003450-290157.png?date=201610260936", "year_graph": "http://chart.finance.daum.net/time3/year/003450-290157.png?date=201610260936"}}, {"model": "stock.stock", "pk": 1893, "fields": {"business": "\uae08\uc735\uc5c5", "title": "\ud604\ub300\ud574\uc0c1", "code": "001450", "yesterday_price": 36600, "price": 35900, "today_start_price": 36250, "max_price": 47550, "min_price": 25650, "high_price": 36450, "low_price": 35550, "change": -1.91, "deal": 33358, "today_graph": "http://chart.finance.daum.net/time3/real/001450-290157.png?date=201610260936", "month_graph": "http://chart.finance.daum.net/candle3/001450-290157.png?date=201610260936", "three_month_graph": "http://chart.finance.daum.net/time3/3month/001450-290157.png?date=201610260936", "year_graph": "http://chart.finance.daum.net/time3/year/001450-290157.png?date=201610260936"}}, {"model": "stock.stock", "pk": 1894, "fields": {"business": "\uae08\uc735\uc5c5", "title": "\ud765\uad6d\ud654\uc7ac", "code": "000540", "yesterday_price": 3445, "price": 3435, "today_start_price": 3460, "max_price": 4475, "min_price": 2415, "high_price": 3460, "low_price": 3430, "change": -0.29, "deal": 1100, "today_graph": "http://chart.finance.daum.net/time3/real/000540-290157.png?date=201610260936", "month_graph": "http://chart.finance.daum.net/candle3/000540-290157.png?date=201610260936", "three_month_graph": "http://chart.finance.daum.net/time3/3month/000540-290157.png?date=201610260936", "year_graph": "http://chart.finance.daum.net/time3/year/000540-290157.png?date=201610260936"}}, {"model": "stock.stock", "pk": 1895, "fields": {"business": "\uae08\uc735\uc5c5", "title": "\ud765\uad6d\ud654\uc7ac2\uc6b0B", "code": "000547", "yesterday_price": 14900, "price": 14900, "today_start_price": 15000, "max_price": 19350, "min_price": 10450, "high_price": 15000, "low_price": 14900, "change": 0.0, "deal": 91, "today_graph": "http://chart.finance.daum.net/time3/real/000547-290157.png?date=201610260936", "month_graph": "http://chart.finance.daum.net/candle3/000547-290157.png?date=201610260936", "three_month_graph": "http://chart.finance.daum.net/time3/3month/000547-290157.png?date=201610260936", "year_graph": "http://chart.finance.daum.net/time3/year/000547-290157.png?date=201610260936"}}, {"model": "stock.stock", "pk": 1896, "fields": {"business": "\uae08\uc735\uc5c5", "title": "\ud765\uad6d\ud654\uc7ac\uc6b0", "code": "000545", "yesterday_price": 3785, "price": 3890, "today_start_price": 3890, "max_price": 4920, "min_price": 2650, "high_price": 3890, "low_price": 3890, "change": 2.77, "deal": 6, "today_graph": "http://chart.finance.daum.net/time3/real/000545-290157.png?date=201610260936", "month_graph": "http://chart.finance.daum.net/candle3/000545-290157.png?date=201610260936", "three_month_graph": "http://chart.finance.daum.net/time3/3month/000545-290157.png?date=201610260936", "year_graph": "http://chart.finance.daum.net/time3/year/000545-290157.png?date=201610260936"}}, {"model": "stock.stock", "pk": 1897, "fields": {"business": "\uae30\uacc4", "title": "KC\ucf54\ud2b8\ub810", "code": "119650", "yesterday_price": 6180, "price": 6070, "today_start_price": 6100, "max_price": 8030, "min_price": 4330, "high_price": 6150, "low_price": 6000, "change": -1.78, "deal": 47690, "today_graph": "http://chart.finance.daum.net/time3/real/119650-290157.png?date=201610260936", "month_graph": "http://chart.finance.daum.net/candle3/119650-290157.png?date=201610260936", "three_month_graph": "http://chart.finance.daum.net/time3/3month/119650-290157.png?date=201610260936", "year_graph": "http://chart.finance.daum.net/time3/year/119650-290157.png?date=201610260936"}}, {"model": "stock.stock", "pk": 1898, "fields": {"business": "\uae30\uacc4", "title": "LIG\ub125\uc2a4\uc6d0", "code": "079550", "yesterday_price": 79200, "price": 78400, "today_start_price": 78500, "max_price": 102500, "min_price": 55500, "high_price": 79200, "low_price": 78000, "change": -1.01, "deal": 6468, "today_graph": "http://chart.finance.daum.net/time3/real/079550-290157.png?date=201610260936", "month_graph": "http://chart.finance.daum.net/candle3/079550-290157.png?date=201610260936", "three_month_graph": "http://chart.finance.daum.net/time3/3month/079550-290157.png?date=201610260936", "year_graph": "http://chart.finance.daum.net/time3/year/079550-290157.png?date=201610260936"}}, {"model": "stock.stock", "pk": 1899, "fields": {"business": "\uae30\uacc4", "title": "S&TC;", "code": "100840", "yesterday_price": 17300, "price": 17100, "today_start_price": 17100, "max_price": 22450, "min_price": 12150, "high_price": 17300, "low_price": 17100, "change": -1.16, "deal": 702, "today_graph": "http://chart.finance.daum.net/time3/real/100840-290157.png?date=201610260936", "month_graph": "http://chart.finance.daum.net/candle3/100840-290157.png?date=201610260936", "three_month_graph": "http://chart.finance.daum.net/time3/3month/100840-290157.png?date=201610260936", "year_graph": "http://chart.finance.daum.net/time3/year/100840-290157.png?date=201610260936"}}, {"model": "stock.stock", "pk": 1900, "fields": {"business": "\uae30\uacc4", "title": "SIMPAC", "code": "009160", "yesterday_price": 5070, "price": 5070, "today_start_price": 5070, "max_price": 6590, "min_price": 3550, "high_price": 5070, "low_price": 5020, "change": 0.0, "deal": 4465, "today_graph": "http://chart.finance.daum.net/time3/real/009160-290157.png?date=201610260936", "month_graph": "http://chart.finance.daum.net/candle3/009160-290157.png?date=201610260936", "three_month_graph": "http://chart.finance.daum.net/time3/3month/009160-290157.png?date=201610260936", "year_graph": "http://chart.finance.daum.net/time3/year/009160-290157.png?date=201610260936"}}, {"model": "stock.stock", "pk": 1901, "fields": {"business": "\uae30\uacc4", "title": "STX\uc5d4\uc9c4", "code": "077970", "yesterday_price": 7250, "price": 7390, "today_start_price": 7300, "max_price": 9420, "min_price": 5080, "high_price": 7420, "low_price": 7240, "change": 1.93, "deal": 10884, "today_graph": "http://chart.finance.daum.net/time3/real/077970-290157.png?date=201610260936", "month_graph": "http://chart.finance.daum.net/candle3/077970-290157.png?date=201610260936", "three_month_graph": "http://chart.finance.daum.net/time3/3month/077970-290157.png?date=201610260936", "year_graph": "http://chart.finance.daum.net/time3/year/077970-290157.png?date=201610260936"}}, {"model": "stock.stock", "pk": 1902, "fields": {"business": "\uae30\uacc4", "title": "STX\uc911\uacf5\uc5c5", "code": "071970", "yesterday_price": 2220, "price": 2255, "today_start_price": 2255, "max_price": 2885, "min_price": 1555, "high_price": 2320, "low_price": 2230, "change": 1.58, "deal": 229315, "today_graph": "http://chart.finance.daum.net/time3/real/071970-290157.png?date=201610260936", "month_graph": "http://chart.finance.daum.net/candle3/071970-290157.png?date=201610260936", "three_month_graph": "http://chart.finance.daum.net/time3/3month/071970-290157.png?date=201610260936", "year_graph": "http://chart.finance.daum.net/time3/year/071970-290157.png?date=201610260936"}}, {"model": "stock.stock", "pk": 1903, "fields": {"business": "\uae30\uacc4", "title": "\uacc4\uc591\uc804\uae30", "code": "012200", "yesterday_price": 5250, "price": 5200, "today_start_price": 5200, "max_price": 6820, "min_price": 3680, "high_price": 5270, "low_price": 5170, "change": -0.95, "deal": 14963, "today_graph": "http://chart.finance.daum.net/time3/real/012200-290157.png?date=201610260936", "month_graph": "http://chart.finance.daum.net/candle3/012200-290157.png?date=201610260936", "three_month_graph": "http://chart.finance.daum.net/time3/3month/012200-290157.png?date=201610260936", "year_graph": "http://chart.finance.daum.net/time3/year/012200-290157.png?date=201610260936"}}, {"model": "stock.stock", "pk": 1904, "fields": {"business": "\uae30\uacc4", "title": "\uacc4\uc591\uc804\uae30\uc6b0", "code": "012205", "yesterday_price": 4245, "price": 4225, "today_start_price": 4245, "max_price": 5510, "min_price": 2975, "high_price": 4280, "low_price": 4170, "change": -0.47, "deal": 6656, "today_graph": "http://chart.finance.daum.net/time3/real/012205-290157.png?date=201610260936", "month_graph": "http://chart.finance.daum.net/candle3/012205-290157.png?date=201610260936", "three_month_graph": "http://chart.finance.daum.net/time3/3month/012205-290157.png?date=201610260936", "year_graph": "http://chart.finance.daum.net/time3/year/012205-290157.png?date=201610260936"}}, {"model": "stock.stock", "pk": 1905, "fields": {"business": "\uae30\uacc4", "title": "\uae30\uc2e0\uc815\uae30", "code": "092440", "yesterday_price": 5270, "price": 5240, "today_start_price": 5250, "max_price": 6850, "min_price": 3690, "high_price": 5250, "low_price": 5240, "change": -0.57, "deal": 901, "today_graph": "http://chart.finance.daum.net/time3/real/092440-290157.png?date=201610260936", "month_graph": "http://chart.finance.daum.net/candle3/092440-290157.png?date=201610260936", "three_month_graph": "http://chart.finance.daum.net/time3/3month/092440-290157.png?date=201610260936", "year_graph": "http://chart.finance.daum.net/time3/year/092440-290157.png?date=201610260936"}}, {"model": "stock.stock", "pk": 1906, "fields": {"business": "\uae30\uacc4", "title": "\ub098\ub77c\ucf00\uc774\uc544\uc774\uc528", "code": "007460", "yesterday_price": 2800, "price": 2745, "today_start_price": 2800, "max_price": 3640, "min_price": 1960, "high_price": 2805, "low_price": 2740, "change": -1.96, "deal": 36924, "today_graph": "http://chart.finance.daum.net/time3/real/007460-290157.png?date=201610260936", "month_graph": "http://chart.finance.daum.net/candle3/007460-290157.png?date=201610260936", "three_month_graph": "http://chart.finance.daum.net/time3/3month/007460-290157.png?date=201610260936", "year_graph": "http://chart.finance.daum.net/time3/year/007460-290157.png?date=201610260936"}}, {"model": "stock.stock", "pk": 1907, "fields": {"business": "\uae30\uacc4", "title": "\ub300\uacbd\uae30\uacc4", "code": "015590", "yesterday_price": 1100, "price": 1105, "today_start_price": 1100, "max_price": 1430, "min_price": 770, "high_price": 1110, "low_price": 1095, "change": 0.45, "deal": 24992, "today_graph": "http://chart.finance.daum.net/time3/real/015590-290157.png?date=201610260936", "month_graph": "http://chart.finance.daum.net/candle3/015590-290157.png?date=201610260936", "three_month_graph": "http://chart.finance.daum.net/time3/3month/015590-290157.png?date=201610260936", "year_graph": "http://chart.finance.daum.net/time3/year/015590-290157.png?date=201610260936"}}, {"model": "stock.stock", "pk": 1908, "fields": {"business": "\uae30\uacc4", "title": "\ub300\ub3d9\uacf5\uc5c5", "code": "000490", "yesterday_price": 7350, "price": 7270, "today_start_price": 7240, "max_price": 9550, "min_price": 5150, "high_price": 7310, "low_price": 7240, "change": -1.09, "deal": 23221, "today_graph": "http://chart.finance.daum.net/time3/real/000490-290157.png?date=201610260936", "month_graph": "http://chart.finance.daum.net/candle3/000490-290157.png?date=201610260936", "three_month_graph": "http://chart.finance.daum.net/time3/3month/000490-290157.png?date=201610260936", "year_graph": "http://chart.finance.daum.net/time3/year/000490-290157.png?date=201610260936"}}, {"model": "stock.stock", "pk": 1909, "fields": {"business": "\uae30\uacc4", "title": "\ub300\ub9bc\ud1b5\uc0c1", "code": "006570", "yesterday_price": 6560, "price": 6420, "today_start_price": 6740, "max_price": 8520, "min_price": 4600, "high_price": 6740, "low_price": 6400, "change": -2.13, "deal": 252, "today_graph": "http://chart.finance.daum.net/time3/real/006570-290157.png?date=201610260936", "month_graph": "http://chart.finance.daum.net/candle3/006570-290157.png?date=201610260936", "three_month_graph": "http://chart.finance.daum.net/time3/3month/006570-290157.png?date=201610260936", "year_graph": "http://chart.finance.daum.net/time3/year/006570-290157.png?date=201610260936"}}, {"model": "stock.stock", "pk": 1910, "fields": {"business": "\uae30\uacc4", "title": "\ub3d9\uc544\uc5d0\uc2a4\ud14d", "code": "058730", "yesterday_price": 5750, "price": 5750, "today_start_price": 5750, "max_price": 7470, "min_price": 4030, "high_price": 5750, "low_price": 5750, "change": 0.0, "deal": 1, "today_graph": "http://chart.finance.daum.net/time3/real/058730-290157.png?date=201610260936", "month_graph": "http://chart.finance.daum.net/candle3/058730-290157.png?date=201610260936", "three_month_graph": "http://chart.finance.daum.net/time3/3month/058730-290157.png?date=201610260936", "year_graph": "http://chart.finance.daum.net/time3/year/058730-290157.png?date=201610260936"}}, {"model": "stock.stock", "pk": 1911, "fields": {"business": "\uae30\uacc4", "title": "\ub3d9\uc591\ubb3c\uc0b0", "code": "002900", "yesterday_price": 2700, "price": 2530, "today_start_price": 2570, "max_price": 3510, "min_price": 1890, "high_price": 2680, "low_price": 2520, "change": -6.3, "deal": 2917011, "today_graph": "http://chart.finance.daum.net/time3/real/002900-290157.png?date=201610260936", "month_graph": "http://chart.finance.daum.net/candle3/002900-290157.png?date=201610260936", "three_month_graph": "http://chart.finance.daum.net/time3/3month/002900-290157.png?date=201610260936", "year_graph": "http://chart.finance.daum.net/time3/year/002900-290157.png?date=201610260936"}}, {"model": "stock.stock", "pk": 1912, "fields": {"business": "\uae30\uacc4", "title": "\ub450\uc0b0\uc5d4\uc9c4", "code": "082740", "yesterday_price": 3700, "price": 3710, "today_start_price": 3660, "max_price": 4810, "min_price": 2590, "high_price": 3720, "low_price": 3650, "change": 0.27, "deal": 57619, "today_graph": "http://chart.finance.daum.net/time3/real/082740-290157.png?date=201610260936", "month_graph": "http://chart.finance.daum.net/candle3/082740-290157.png?date=201610260936", "three_month_graph": "http://chart.finance.daum.net/time3/3month/082740-290157.png?date=201610260936", "year_graph": "http://chart.finance.daum.net/time3/year/082740-290157.png?date=201610260936"}}, {"model": "stock.stock", "pk": 1913, "fields": {"business": "\uae30\uacc4", "title": "\ub450\uc0b0\uc778\ud504\ub77c\ucf54\uc5b4", "code": "042670", "yesterday_price": 7090, "price": 6980, "today_start_price": 7040, "max_price": 9210, "min_price": 4970, "high_price": 7070, "low_price": 6950, "change": -1.55, "deal": 251680, "today_graph": "http://chart.finance.daum.net/time3/real/042670-290157.png?date=201610260936", "month_graph": "http://chart.finance.daum.net/candle3/042670-290157.png?date=201610260936", "three_month_graph": "http://chart.finance.daum.net/time3/3month/042670-290157.png?date=201610260936", "year_graph": "http://chart.finance.daum.net/time3/year/042670-290157.png?date=201610260936"}}, {"model": "stock.stock", "pk": 1914, "fields": {"business": "\uae30\uacc4", "title": "\ub450\uc0b0\uc911\uacf5\uc5c5", "code": "034020", "yesterday_price": 27600, "price": 27400, "today_start_price": 27600, "max_price": 35850, "min_price": 19350, "high_price": 27600, "low_price": 27150, "change": -0.72, "deal": 51808, "today_graph": "http://chart.finance.daum.net/time3/real/034020-290157.png?date=201610260936", "month_graph": "http://chart.finance.daum.net/candle3/034020-290157.png?date=201610260936", "three_month_graph": "http://chart.finance.daum.net/time3/3month/034020-290157.png?date=201610260936", "year_graph": "http://chart.finance.daum.net/time3/year/034020-290157.png?date=201610260936"}}, {"model": "stock.stock", "pk": 1915, "fields": {"business": "\uae30\uacc4", "title": "\ub514\uc640\uc774\ud30c\uc6cc", "code": "210540", "yesterday_price": 6250, "price": 6210, "today_start_price": 6230, "max_price": 8120, "min_price": 4380, "high_price": 6300, "low_price": 6210, "change": -0.64, "deal": 4496, "today_graph": "http://chart.finance.daum.net/time3/real/210540-290157.png?date=201610260936", "month_graph": "http://chart.finance.daum.net/candle3/210540-290157.png?date=201610260936", "three_month_graph": "http://chart.finance.daum.net/time3/3month/210540-290157.png?date=201610260936", "year_graph": "http://chart.finance.daum.net/time3/year/210540-290157.png?date=201610260936"}}, {"model": "stock.stock", "pk": 1916, "fields": {"business": "\uae30\uacc4", "title": "\uc0bc\uc775THK", "code": "004380", "yesterday_price": 10850, "price": 10800, "today_start_price": 10900, "max_price": 14100, "min_price": 7600, "high_price": 10950, "low_price": 10800, "change": -0.46, "deal": 11484, "today_graph": "http://chart.finance.daum.net/time3/real/004380-290157.png?date=201610260936", "month_graph": "http://chart.finance.daum.net/candle3/004380-290157.png?date=201610260936", "three_month_graph": "http://chart.finance.daum.net/time3/3month/004380-290157.png?date=201610260936", "year_graph": "http://chart.finance.daum.net/time3/year/004380-290157.png?date=201610260936"}}, {"model": "stock.stock", "pk": 1917, "fields": {"business": "\uae30\uacc4", "title": "\uc0bc\ud654\uc655\uad00", "code": "004450", "yesterday_price": 45900, "price": 45450, "today_start_price": 45550, "max_price": 59600, "min_price": 32150, "high_price": 45700, "low_price": 45450, "change": -0.98, "deal": 38, "today_graph": "http://chart.finance.daum.net/time3/real/004450-290157.png?date=201610260936", "month_graph": "http://chart.finance.daum.net/candle3/004450-290157.png?date=201610260936", "three_month_graph": "http://chart.finance.daum.net/time3/3month/004450-290157.png?date=201610260936", "year_graph": "http://chart.finance.daum.net/time3/year/004450-290157.png?date=201610260936"}}, {"model": "stock.stock", "pk": 1918, "fields": {"business": "\uae30\uacc4", "title": "\uc138\uc6d0\uc140\ub860\ud14d", "code": "091090", "yesterday_price": 3140, "price": 3100, "today_start_price": 3135, "max_price": 4080, "min_price": 2200, "high_price": 3165, "low_price": 3085, "change": -1.27, "deal": 32903, "today_graph": "http://chart.finance.daum.net/time3/real/091090-290157.png?date=201610260936", "month_graph": "http://chart.finance.daum.net/candle3/091090-290157.png?date=201610260936", "three_month_graph": "http://chart.finance.daum.net/time3/3month/091090-290157.png?date=201610260936", "year_graph": "http://chart.finance.daum.net/time3/year/091090-290157.png?date=201610260936"}}, {"model": "stock.stock", "pk": 1919, "fields": {"business": "\uae30\uacc4", "title": "\uc138\ud654\uc544\uc774\uc5e0\uc528", "code": "145210", "yesterday_price": 7340, "price": 7280, "today_start_price": 7330, "max_price": 9540, "min_price": 5140, "high_price": 7340, "low_price": 7280, "change": -0.82, "deal": 1689, "today_graph": "http://chart.finance.daum.net/time3/real/145210-290157.png?date=201610260936", "month_graph": "http://chart.finance.daum.net/candle3/145210-290157.png?date=201610260936", "three_month_graph": "http://chart.finance.daum.net/time3/3month/145210-290157.png?date=201610260936", "year_graph": "http://chart.finance.daum.net/time3/year/145210-290157.png?date=201610260936"}}, {"model": "stock.stock", "pk": 1920, "fields": {"business": "\uae30\uacc4", "title": "\uc218\uc0b0\uc911\uacf5\uc5c5", "code": "017550", "yesterday_price": 2035, "price": 2080, "today_start_price": 2020, "max_price": 2645, "min_price": 1425, "high_price": 2120, "low_price": 2005, "change": 2.21, "deal": 364949, "today_graph": "http://chart.finance.daum.net/time3/real/017550-290157.png?date=201610260936", "month_graph": "http://chart.finance.daum.net/candle3/017550-290157.png?date=201610260936", "three_month_graph": "http://chart.finance.daum.net/time3/3month/017550-290157.png?date=201610260936", "year_graph": "http://chart.finance.daum.net/time3/year/017550-290157.png?date=201610260936"}}, {"model": "stock.stock", "pk": 1921, "fields": {"business": "\uae30\uacc4", "title": "\uc2e0\uc131\uc5d0\ud504\uc5d0\uc774", "code": "104120", "yesterday_price": 4430, "price": 4335, "today_start_price": 4380, "max_price": 5750, "min_price": 3105, "high_price": 4495, "low_price": 4335, "change": -2.14, "deal": 20328, "today_graph": "http://chart.finance.daum.net/time3/real/104120-290157.png?date=201610260936", "month_graph": "http://chart.finance.daum.net/candle3/104120-290157.png?date=201610260936", "three_month_graph": "http://chart.finance.daum.net/time3/3month/104120-290157.png?date=201610260936", "year_graph": "http://chart.finance.daum.net/time3/year/104120-290157.png?date=201610260936"}}, {"model": "stock.stock", "pk": 1922, "fields": {"business": "\uae30\uacc4", "title": "\uc2e0\uc131\uc774\uc5d4\uc9c0", "code": "104110", "yesterday_price": 4360, "price": 4280, "today_start_price": 4335, "max_price": 5660, "min_price": 3055, "high_price": 4380, "low_price": 4270, "change": -1.83, "deal": 27242, "today_graph": "http://chart.finance.daum.net/time3/real/104110-290157.png?date=201610260936", "month_graph": "http://chart.finance.daum.net/candle3/104110-290157.png?date=201610260936", "three_month_graph": "http://chart.finance.daum.net/time3/3month/104110-290157.png?date=201610260936", "year_graph": "http://chart.finance.daum.net/time3/year/104110-290157.png?date=201610260936"}}, {"model": "stock.stock", "pk": 1923, "fields": {"business": "\uae30\uacc4", "title": "\uc528\uc5d0\uc2a4\uc708\ub4dc", "code": "112610", "yesterday_price": 25300, "price": 24900, "today_start_price": 25250, "max_price": 32850, "min_price": 17750, "high_price": 25500, "low_price": 24850, "change": -1.58, "deal": 14913, "today_graph": "http://chart.finance.daum.net/time3/real/112610-290157.png?date=201610260936", "month_graph": "http://chart.finance.daum.net/candle3/112610-290157.png?date=201610260936", "three_month_graph": "http://chart.finance.daum.net/time3/3month/112610-290157.png?date=201610260936", "year_graph": "http://chart.finance.daum.net/time3/year/112610-290157.png?date=201610260936"}}, {"model": "stock.stock", "pk": 1924, "fields": {"business": "\uae30\uacc4", "title": "\uc5d4\ucf00\uc774", "code": "085310", "yesterday_price": 4465, "price": 4720, "today_start_price": 4520, "max_price": 5800, "min_price": 3130, "high_price": 4845, "low_price": 4490, "change": 5.71, "deal": 772232, "today_graph": "http://chart.finance.daum.net/time3/real/085310-290157.png?date=201610260936", "month_graph": "http://chart.finance.daum.net/candle3/085310-290157.png?date=201610260936", "three_month_graph": "http://chart.finance.daum.net/time3/3month/085310-290157.png?date=201610260936", "year_graph": "http://chart.finance.daum.net/time3/year/085310-290157.png?date=201610260936"}}, {"model": "stock.stockmanager", "pk": 1, "fields": {"user": 2, "stock": 1789, "request_flag": true, "request_price": 28700, "count": 1, "total_price": 0, "when_price": 29950, "flag": true, "request_cancel": false, "user_money": 0, "create_time": "2016-10-26T14:09:40.145Z"}}]